divisor verilog/control_div.v
module control_div(clk, rst, start, sign_r, z, load_v, load_q, shift_rq, set_q0, force_add, reset, load_r, init_c, dec_c, done);
input clk;
input rst;
input start;
input sign_r;
input z;
output load_v;
output load_q;
output shift_rq;
output set_q0;
output force_add;
output reset;
output load_r;
output init_c;
output dec_c;
output done;

reg load_v;
reg load_q;
reg shift_rq;
reg set_q0;
reg force_add;
reg reset;
reg load_r;
reg init_c;
reg dec_c;
reg done;

reg [2:0] state, next_state;
reg flag_just_operated;

parameter S_START = 3'd0; 
parameter S_INIT = 3'd1;
parameter S_CHECK_C = 3'd2;
parameter S_SHIFT = 3'd3;
parameter S_ADDSUB = 3'd4;
parameter S_END_CHECK = 3'd5;
parameter S_CORRECT = 3'd6;
parameter S_FINISH = 3'd7;

always @(posedge clk) begin
    if (rst) begin
        state <= S_START;
        flag_just_operated <= 1'b0;
    end else begin
        state <= next_state;
        if (state == S_ADDSUB) 
            flag_just_operated <= 1'b1;
        else 
            flag_just_operated <= 1'b0;
    end
end

always @(*) begin
    load_v = 0; load_q = 0; shift_rq = 0; set_q0 = 0; force_add = 0;
    reset = 0; load_r = 0; init_c = 0; dec_c = 0; done = 0;
    next_state = state;

    case (state)
        S_START: begin
            if (start) next_state = S_INIT;
        end
        S_INIT: begin
            load_v = 1;
            load_q = 1;
            reset = 1;
            init_c = 1;
            next_state = S_CHECK_C;
        end
        S_CHECK_C: begin
            if (flag_just_operated && !sign_r) begin
                set_q0 = 1; 
            end
            if (z) next_state = S_END_CHECK;
            else next_state = S_SHIFT;
        end
        S_SHIFT: begin
            shift_rq = 1;
            next_state = S_ADDSUB;
        end
        S_ADDSUB: begin
            load_r = 1;
            dec_c = 1;
            next_state = S_CHECK_C;
        end
        S_END_CHECK: begin
            if (sign_r) next_state = S_CORRECT;
            else next_state = S_FINISH;
        end
        S_CORRECT: begin
            force_add = 1;
            load_r = 1;
            next_state = S_FINISH;
        end
        S_FINISH: begin
            done = 1;
            next_state = S_START;
        end
        default: next_state = S_START;
    endcase
end

endmodule

divisor verilog/comp.v
module comp(clk, rst, init_c, dec_c, z);
input clk;
input rst;
input init_c;
input dec_c;
output z;

reg [4:0] count;

assign z = (count == 5'd0);

always @(posedge clk) begin
    if (init_c) begin
        count <= 5'd16;
    end else if (rst) begin
        count <= 5'd0;
    end else if (dec_c) begin
        count <= count - 5'd1;
    end
end

endmodule

divisor verilog/alu.v
module alu(in_R, in_V, force_add, sign_r, alu_out);
input [16:0] in_R;
input [15:0] in_V;
input force_add;
input sign_r;
output [16:0] alu_out;

wire [16:0] ext_V;

assign ext_V = {1'b0, in_V};
assign alu_out = (force_add | sign_r) ? (in_R + ext_V) : (in_R - ext_V);

endmodule

divisor verilog/reg_r.v
module reg_r(clk, rst, shift_rq, load_r, in_msb_q, alu_out, out_R, sign_r);
input clk;
input rst;
input shift_rq;
input load_r;
input in_msb_q;
input [16:0] alu_out;
output [16:0] out_R;
output sign_r;

reg [16:0] out_R;

assign sign_r = out_R[16];

always @(posedge clk) begin
    if (rst) begin
        out_R <= 17'd0;
    end else if (load_r) begin
        out_R <= alu_out;
    end else if (shift_rq) begin
        out_R <= {out_R[15:0], in_msb_q};
    end
end

endmodule

divisor verilog/reg_q.v
module reg_q(clk, load_q, shift_rq, set_q0, in_D, msb_q, out_Q);
input clk;
input load_q;
input shift_rq;
input set_q0;
input [15:0] in_D;
output msb_q;
output [15:0] out_Q;

reg [15:0] out_Q;

assign msb_q = out_Q[15];

always @(posedge clk) begin
    if (load_q) begin
        out_Q <= in_D;
    end else if (shift_rq) begin
        out_Q <= {out_Q[14:0], 1'b0};
    end else if (set_q0) begin
        out_Q[0] <= 1'b1;
    end
end

endmodule

divisor verilog/reg_v.v
module reg_v(clk,load_v,in_V,out_V);
input clk;
input load_v;
input [15:0] in_V;
output [15:0] out_V;

reg [15:0] out_V;

always @(posedge clk) begin
    if (load_v) begin
        out_V <= in_V;
    end
end

endmodule

divisor verilog/div.v
module div(clk,rst,start,D,V,Q,R,done);
input rst;
input clk;
input start;
input [15:0]D;
input [15:0]V;
output[15:0]Q;
output[16:0]R;
output done;

wire w_load_v;
wire w_load_q;
wire w_shift_rq;
wire w_set_q0;
wire w_force_add;
wire w_reset;
wire w_load_r;
wire w_init_c;
wire w_dec_c;
wire w_zero;
wire w_sign_r;
wire w_msb_q;

wire [15:0]w_V;
wire [16:0]w_alu_out;

reg_v reg_v0 (.clk(clk), .load_v(w_load_v), .in_V(V), .out_V(w_V));
reg_q reg_q0 (.clk(clk), .load_q(w_load_q), .shift_rq(w_shift_rq), .set_q0(w_set_q0), .in_D(D), .msb_q(w_msb_q), .out_Q(Q));
reg_r reg_r0 (.clk(clk), .rst(w_reset), .shift_rq(w_shift_rq), .load_r(w_load_r), .in_msb_q(w_msb_q), .alu_out(w_alu_out), .out_R(R), .sign_r(w_sign_r));
alu alu0 (.in_R(R), .in_V(w_V), .force_add(w_force_add), .sign_r(w_sign_r), .alu_out(w_alu_out));
comp comp0 (.clk(clk), .rst(w_reset), .init_c(w_init_c), .dec_c(w_dec_c), .z(w_zero));
control_div control0 (.clk(clk), .rst(rst), .start(start), .sign_r(w_sign_r), .z(w_zero), .load_v(w_load_v), .load_q(w_load_q), .shift_rq(w_shift_rq), .set_q0(w_set_q0), .force_add(w_force_add), .reset(w_reset), .load_r(w_load_r), .init_c(w_init_c), .dec_c(w_dec_c), .done(done));

endmodule

divisor verilog/div_tb.v
module div_tb;

    // Entradas al top module
    reg clk;
    reg rst;
    reg start;
    reg [15:0] D;
    reg [15:0] V;

    // Salidas del top module
    wire [15:0] Q;
    wire [16:0] R;
    wire done;

    // Instancia del nuevo top module
    div uut (
        .clk(clk), 
        .rst(rst), 
        .start(start), 
        .D(D), 
        .V(V), 
        .Q(Q), 
        .R(R), 
        .done(done)
    );

    // Generador de reloj (Periodo = 10)
    always #5 clk = ~clk;

    // Pruebas
    
    initial begin
        $dumpfile("simulacion_div.vcd");
        $dumpvars(0, div_tb);

        // Condiciones iniciales
        clk = 0;
        rst = 1;
        start = 0;
        D = 16'd0;
        V = 16'd0;

        // Quitar reset
        #20;
        rst = 0;
        
        // ---------------------------------------------------
        // Prueba 1: Dividir 45 entre 6 (Esperado: Q=7, R=3)
        // ---------------------------------------------------
        #10;
        D = 16'd45;
        V = 16'd6;
        
        @(posedge clk);
        start = 1;
        @(posedge clk);
        start = 0;
        
        // Esperar a que termine la división
        while (!done) begin
            @(posedge clk);
        end
        
        $display("Prueba 1 Terminada: 45 / 6 -> Cociente = %d, Residuo = %d", Q, R);

        // ---------------------------------------------------
        // Prueba 2: Dividir 100 entre 15 (Esperado: Q=6, R=10)
        // ---------------------------------------------------
        #20;
        D = 16'd100;
        V = 16'd15;
        
        @(posedge clk);
        start = 1;
        @(posedge clk);
        start = 0;
        
        while (!done) begin
            @(posedge clk);
        end
        
        $display("Prueba 2 Terminada: 100 / 15 -> Cociente = %d, Residuo = %d", Q, R);

        // Finalizar simulación
        #20;
        $finish;
    end

endmodule

divisor verilog/simulacion_div.vcd
$date
	Mon Jul 13 13:11:52 2026
$end
$version
	Icarus Verilog
$end
$timescale
	1s
$end
$scope module div_tb $end
$var wire 1 ! done $end
$var wire 17 " R [16:0] $end
$var wire 16 # Q [15:0] $end
$var reg 16 $ D [15:0] $end
$var reg 16 % V [15:0] $end
$var reg 1 & clk $end
$var reg 1 ' rst $end
$var reg 1 ( start $end
$scope module uut $end
$var wire 16 ) D [15:0] $end
$var wire 16 * V [15:0] $end
$var wire 1 & clk $end
$var wire 1 ' rst $end
$var wire 1 ( start $end
$var wire 1 + w_zero $end
$var wire 1 , w_sign_r $end
$var wire 1 - w_shift_rq $end
$var wire 1 . w_set_q0 $end
$var wire 1 / w_reset $end
$var wire 1 0 w_msb_q $end
$var wire 1 1 w_load_v $end
$var wire 1 2 w_load_r $end
$var wire 1 3 w_load_q $end
$var wire 1 4 w_init_c $end
$var wire 1 5 w_force_add $end
$var wire 1 6 w_dec_c $end
$var wire 17 7 w_alu_out [16:0] $end
$var wire 16 8 w_V [15:0] $end
$var wire 1 ! done $end
$var wire 17 9 R [16:0] $end
$var wire 16 : Q [15:0] $end
$scope module alu0 $end
$var wire 1 , sign_r $end
$var wire 16 ; in_V [15:0] $end
$var wire 17 < in_R [16:0] $end
$var wire 1 5 force_add $end
$var wire 17 = ext_V [16:0] $end
$var wire 17 > alu_out [16:0] $end
$upscope $end
$scope module comp0 $end
$var wire 1 & clk $end
$var wire 1 + z $end
$var wire 1 / rst $end
$var wire 1 4 init_c $end
$var wire 1 6 dec_c $end
$var reg 5 ? count [4:0] $end
$upscope $end
$scope module control0 $end
$var wire 1 & clk $end
$var wire 1 ' rst $end
$var wire 1 ( start $end
$var wire 1 + z $end
$var wire 1 , sign_r $end
$var reg 1 6 dec_c $end
$var reg 1 ! done $end
$var reg 1 @ flag_just_operated $end
$var reg 1 5 force_add $end
$var reg 1 4 init_c $end
$var reg 1 3 load_q $end
$var reg 1 2 load_r $end
$var reg 1 1 load_v $end
$var reg 3 A next_state [2:0] $end
$var reg 1 / reset $end
$var reg 1 . set_q0 $end
$var reg 1 - shift_rq $end
$var reg 3 B state [2:0] $end
$upscope $end
$scope module reg_q0 $end
$var wire 1 & clk $end
$var wire 16 C in_D [15:0] $end
$var wire 1 3 load_q $end
$var wire 1 . set_q0 $end
$var wire 1 - shift_rq $end
$var wire 1 0 msb_q $end
$var reg 16 D out_Q [15:0] $end
$upscope $end
$scope module reg_r0 $end
$var wire 17 E alu_out [16:0] $end
$var wire 1 & clk $end
$var wire 1 0 in_msb_q $end
$var wire 1 2 load_r $end
$var wire 1 / rst $end
$var wire 1 - shift_rq $end
$var wire 1 , sign_r $end
$var reg 17 F out_R [16:0] $end
$upscope $end
$scope module reg_v0 $end
$var wire 1 & clk $end
$var wire 16 G in_V [15:0] $end
$var wire 1 1 load_v $end
$var reg 16 H out_V [15:0] $end
$upscope $end
$upscope $end
$upscope $end
$enddefinitions $end
#0
$dumpvars
bx H
b0 G
bx F
bx E
bx D
b0 C
bx B
b0 A
x@
bx ?
bx >
b0xxxxxxxxxxxxxxxx =
bx <
bx ;
bx :
bx 9
bx 8
bx 7
06
05
04
03
02
01
x0
0/
0.
0-
x,
x+
b0 *
b0 )
0(
1'
0&
b0 %
b0 $
bx #
bx "
0!
$end
#5
0@
b0 B
1&
#10
0&
#15
1&
#20
0&
0'
#25
1&
#30
0&
b110 %
b110 *
b110 G
b101101 $
b101101 )
b101101 C
#35
b1 A
1(
1&
#40
0&
#45
14
1/
13
11
b1 B
b10 A
0(
1&
#50
0&
#55
b11 A
04
0/
03
01
0,
b11111111111111010 7
b11111111111111010 >
b11111111111111010 E
00
b10 B
0+
b10000 ?
b0 "
b0 9
b0 <
b0 F
b101101 #
b101101 :
b101101 D
b110 =
b110 8
b110 ;
b110 H
1&
#60
0&
#65
b100 A
1-
b11 B
1&
#70
0&
#75
b10 A
16
12
0-
b100 B
b1011010 #
b1011010 :
b1011010 D
1&
#80
0&
#85
1,
b0 7
b0 >
b0 E
b11 A
0.
06
02
b11111111111111010 "
b11111111111111010 9
b11111111111111010 <
b11111111111111010 F
b1111 ?
1@
b10 B
1&
#90
0&
#95
b100 A
1-
0@
b11 B
1&
#100
0&
#105
b11111111111111010 7
b11111111111111010 >
b11111111111111010 E
b10 A
16
12
0-
b10110100 #
b10110100 :
b10110100 D
b11111111111110100 "
b11111111111110100 9
b11111111111110100 <
b11111111111110100 F
b100 B
1&
#110
0&
#115
b11 A
06
02
b0 7
b0 >
b0 E
1@
b10 B
b1110 ?
b11111111111111010 "
b11111111111111010 9
b11111111111111010 <
b11111111111111010 F
1&
#120
0&
#125
b100 A
1-
0@
b11 B
1&
#130
0&
#135
b10 A
16
12
0-
b11111111111111010 7
b11111111111111010 >
b11111111111111010 E
b100 B
b11111111111110100 "
b11111111111110100 9
b11111111111110100 <
b11111111111110100 F
b101101000 #
b101101000 :
b101101000 D
1&
#140
0&
#145
b0 7
b0 >
b0 E
b11 A
06
02
b11111111111111010 "
b11111111111111010 9
b11111111111111010 <
b11111111111111010 F
b1101 ?
1@
b10 B
1&
#150
0&
#155
b100 A
1-
0@
b11 B
1&
#160
0&
#165
b11111111111111010 7
b11111111111111010 >
b11111111111111010 E
b10 A
16
12
0-
b1011010000 #
b1011010000 :
b1011010000 D
b11111111111110100 "
b11111111111110100 9
b11111111111110100 <
b11111111111110100 F
b100 B
1&
#170
0&
#175
b11 A
06
02
b0 7
b0 >
b0 E
1@
b10 B
b1100 ?
b11111111111111010 "
b11111111111111010 9
b11111111111111010 <
b11111111111111010 F
1&
#180
0&
#185
b100 A
1-
0@
b11 B
1&
#190
0&
#195
b10 A
16
12
0-
b11111111111111010 7
b11111111111111010 >
b11111111111111010 E
b100 B
b11111111111110100 "
b11111111111110100 9
b11111111111110100 <
b11111111111110100 F
b10110100000 #
b10110100000 :
b10110100000 D
1&
#200
0&
#205
b0 7
b0 >
b0 E
b11 A
06
02
b11111111111111010 "
b11111111111111010 9
b11111111111111010 <
b11111111111111010 F
b1011 ?
1@
b10 B
1&
#210
0&
#215
b100 A
1-
0@
b11 B
1&
#220
0&
#225
b11111111111111010 7
b11111111111111010 >
b11111111111111010 E
b10 A
16
12
0-
b101101000000 #
b101101000000 :
b101101000000 D
b11111111111110100 "
b11111111111110100 9
b11111111111110100 <
b11111111111110100 F
b100 B
1&
#230
0&
#235
b11 A
06
02
b0 7
b0 >
b0 E
1@
b10 B
b1010 ?
b11111111111111010 "
b11111111111111010 9
b11111111111111010 <
b11111111111111010 F
1&
#240
0&
#245
b100 A
1-
0@
b11 B
1&
#250
0&
#255
b10 A
16
12
0-
b11111111111111010 7
b11111111111111010 >
b11111111111111010 E
b100 B
b11111111111110100 "
b11111111111110100 9
b11111111111110100 <
b11111111111110100 F
b1011010000000 #
b1011010000000 :
b1011010000000 D
1&
#260
0&
#265
b0 7
b0 >
b0 E
b11 A
06
02
b11111111111111010 "
b11111111111111010 9
b11111111111111010 <
b11111111111111010 F
b1001 ?
1@
b10 B
1&
#270
0&
#275
b100 A
1-
0@
b11 B
1&
#280
0&
#285
b11111111111111010 7
b11111111111111010 >
b11111111111111010 E
b10 A
16
12
0-
b10110100000000 #
b10110100000000 :
b10110100000000 D
b11111111111110100 "
b11111111111110100 9
b11111111111110100 <
b11111111111110100 F
b100 B
1&
#290
0&
#295
b11 A
06
02
b0 7
b0 >
b0 E
1@
b10 B
b1000 ?
b11111111111111010 "
b11111111111111010 9
b11111111111111010 <
b11111111111111010 F
1&
#300
0&
#305
b100 A
1-
0@
b11 B
1&
#310
0&
#315
b10 A
16
12
0-
b11111111111111010 7
b11111111111111010 >
b11111111111111010 E
b100 B
b11111111111110100 "
b11111111111110100 9
b11111111111110100 <
b11111111111110100 F
b101101000000000 #
b101101000000000 :
b101101000000000 D
1&
#320
0&
#325
b0 7
b0 >
b0 E
b11 A
06
02
b11111111111111010 "
b11111111111111010 9
b11111111111111010 <
b11111111111111010 F
b111 ?
1@
b10 B
1&
#330
0&
#335
b100 A
1-
0@
b11 B
1&
#340
0&
#345
10
b11111111111111010 7
b11111111111111010 >
b11111111111111010 E
b10 A
16
12
0-
b1011010000000000 #
b1011010000000000 :
b1011010000000000 D
b11111111111110100 "
b11111111111110100 9
b11111111111110100 <
b11111111111110100 F
b100 B
1&
#350
0&
#355
b11 A
06
02
b0 7
b0 >
b0 E
1@
b10 B
b110 ?
b11111111111111010 "
b11111111111111010 9
b11111111111111010 <
b11111111111111010 F
1&
#360
0&
#365
b100 A
1-
0@
b11 B
1&
#370
0&
#375
b10 A
16
12
0-
b11111111111111011 7
b11111111111111011 >
b11111111111111011 E
00
b100 B
b11111111111110101 "
b11111111111110101 9
b11111111111110101 <
b11111111111110101 F
b110100000000000 #
b110100000000000 :
b110100000000000 D
1&
#380
0&
#385
b1 7
b1 >
b1 E
b11 A
06
02
b11111111111111011 "
b11111111111111011 9
b11111111111111011 <
b11111111111111011 F
b101 ?
1@
b10 B
1&
#390
0&
#395
b100 A
1-
0@
b11 B
1&
#400
0&
#405
10
b11111111111111100 7
b11111111111111100 >
b11111111111111100 E
b10 A
16
12
0-
b1101000000000000 #
b1101000000000000 :
b1101000000000000 D
b11111111111110110 "
b11111111111110110 9
b11111111111110110 <
b11111111111110110 F
b100 B
1&
#410
0&
#415
b11 A
06
02
b10 7
b10 >
b10 E
1@
b10 B
b100 ?
b11111111111111100 "
b11111111111111100 9
b11111111111111100 <
b11111111111111100 F
1&
#420
0&
#425
b100 A
1-
0@
b11 B
1&
#430
0&
#435
b10 A
16
12
0-
b11111111111111111 7
b11111111111111111 >
b11111111111111111 E
b100 B
b11111111111111001 "
b11111111111111001 9
b11111111111111001 <
b11111111111111001 F
b1010000000000000 #
b1010000000000000 :
b1010000000000000 D
1&
#440
0&
#445
b101 7
b101 >
b101 E
b11 A
06
02
b11111111111111111 "
b11111111111111111 9
b11111111111111111 <
b11111111111111111 F
b11 ?
1@
b10 B
1&
#450
0&
#455
b100 A
1-
0@
b11 B
1&
#460
0&
#465
00
b10 A
16
12
0-
b100000000000000 #
b100000000000000 :
b100000000000000 D
b100 B
1&
#470
0&
#475
b11 A
1.
06
02
0,
b11111111111111111 7
b11111111111111111 >
b11111111111111111 E
1@
b10 B
b10 ?
b101 "
b101 9
b101 <
b101 F
1&
#480
0&
#485
b100 A
1-
0.
b100000000000001 #
b100000000000001 :
b100000000000001 D
0@
b11 B
1&
#490
0&
#495
b10 A
16
12
0-
b100 7
b100 >
b100 E
10
b100 B
b1010 "
b1010 9
b1010 <
b1010 F
b1000000000000010 #
b1000000000000010 :
b1000000000000010 D
1&
#500
0&
#505
b11111111111111110 7
b11111111111111110 >
b11111111111111110 E
b11 A
1.
06
02
b100 "
b100 9
b100 <
b100 F
b1 ?
1@
b10 B
1&
#510
0&
#515
b100 A
1-
0.
0@
b11 B
b1000000000000011 #
b1000000000000011 :
b1000000000000011 D
1&
#520
0&
#525
00
b11 7
b11 >
b11 E
b10 A
16
12
0-
b110 #
b110 :
b110 D
b1001 "
b1001 9
b1001 <
b1001 F
b100 B
1&
#530
0&
#535
b101 A
1.
06
02
b11111111111111101 7
b11111111111111101 >
b11111111111111101 E
1@
b10 B
1+
b0 ?
b11 "
b11 9
b11 <
b11 F
1&
#540
0&
#545
b111 A
0.
b111 #
b111 :
b111 D
0@
b101 B
1&
#550
0&
#555
b0 A
1!
b111 B
1&
#560
0&
#565
0!
b0 B
1&
#570
0&
#575
1&
#580
0&
#585
b1 A
1(
1&
b1111 %
b1111 *
b1111 G
b1100100 $
b1100100 )
b1100100 C
#590
0&
#595
14
1/
13
11
b1 B
b10 A
0(
1&
#600
0&
#605
b11111111111110001 7
b11111111111110001 >
b11111111111110001 E
b11 A
04
0/
03
01
b1111 =
b1111 8
b1111 ;
b1111 H
b1100100 #
b1100100 :
b1100100 D
b0 "
b0 9
b0 <
b0 F
0+
b10000 ?
b10 B
1&
#610
0&
#615
b100 A
1-
b11 B
1&
#620
0&
#625
b10 A
16
12
0-
b11001000 #
b11001000 :
b11001000 D
b100 B
1&
#630
0&
#635
b11 A
06
02
1,
b0 7
b0 >
b0 E
1@
b10 B
b1111 ?
b11111111111110001 "
b11111111111110001 9
b11111111111110001 <
b11111111111110001 F
1&
#640
0&
#645
b100 A
1-
0@
b11 B
1&
#650
0&
#655
b10 A
16
12
0-
b11111111111110001 7
b11111111111110001 >
b11111111111110001 E
b100 B
b11111111111100010 "
b11111111111100010 9
b11111111111100010 <
b11111111111100010 F
b110010000 #
b110010000 :
b110010000 D
1&
#660
0&
#665
b0 7
b0 >
b0 E
b11 A
06
02
b11111111111110001 "
b11111111111110001 9
b11111111111110001 <
b11111111111110001 F
b1110 ?
1@
b10 B
1&
#670
0&
#675
b100 A
1-
0@
b11 B
1&
#680
0&
#685
b11111111111110001 7
b11111111111110001 >
b11111111111110001 E
b10 A
16
12
0-
b1100100000 #
b1100100000 :
b1100100000 D
b11111111111100010 "
b11111111111100010 9
b11111111111100010 <
b11111111111100010 F
b100 B
1&
#690
0&
#695
b11 A
06
02
b0 7
b0 >
b0 E
1@
b10 B
b1101 ?
b11111111111110001 "
b11111111111110001 9
b11111111111110001 <
b11111111111110001 F
1&
#700
0&
#705
b100 A
1-
0@
b11 B
1&
#710
0&
#715
b10 A
16
12
0-
b11111111111110001 7
b11111111111110001 >
b11111111111110001 E
b100 B
b11111111111100010 "
b11111111111100010 9
b11111111111100010 <
b11111111111100010 F
b11001000000 #
b11001000000 :
b11001000000 D
1&
#720
0&
#725
b0 7
b0 >
b0 E
b11 A
06
02
b11111111111110001 "
b11111111111110001 9
b11111111111110001 <
b11111111111110001 F
b1100 ?
1@
b10 B
1&
#730
0&
#735
b100 A
1-
0@
b11 B
1&
#740
0&
#745
b11111111111110001 7
b11111111111110001 >
b11111111111110001 E
b10 A
16
12
0-
b110010000000 #
b110010000000 :
b110010000000 D
b11111111111100010 "
b11111111111100010 9
b11111111111100010 <
b11111111111100010 F
b100 B
1&
#750
0&
#755
b11 A
06
02
b0 7
b0 >
b0 E
1@
b10 B
b1011 ?
b11111111111110001 "
b11111111111110001 9
b11111111111110001 <
b11111111111110001 F
1&
#760
0&
#765
b100 A
1-
0@
b11 B
1&
#770
0&
#775
b10 A
16
12
0-
b11111111111110001 7
b11111111111110001 >
b11111111111110001 E
b100 B
b11111111111100010 "
b11111111111100010 9
b11111111111100010 <
b11111111111100010 F
b1100100000000 #
b1100100000000 :
b1100100000000 D
1&
#780
0&
#785
b0 7
b0 >
b0 E
b11 A
06
02
b11111111111110001 "
b11111111111110001 9
b11111111111110001 <
b11111111111110001 F
b1010 ?
1@
b10 B
1&
#790
0&
#795
b100 A
1-
0@
b11 B
1&
#800
0&
#805
b11111111111110001 7
b11111111111110001 >
b11111111111110001 E
b10 A
16
12
0-
b11001000000000 #
b11001000000000 :
b11001000000000 D
b11111111111100010 "
b11111111111100010 9
b11111111111100010 <
b11111111111100010 F
b100 B
1&
#810
0&
#815
b11 A
06
02
b0 7
b0 >
b0 E
1@
b10 B
b1001 ?
b11111111111110001 "
b11111111111110001 9
b11111111111110001 <
b11111111111110001 F
1&
#820
0&
#825
b100 A
1-
0@
b11 B
1&
#830
0&
#835
b10 A
16
12
0-
b11111111111110001 7
b11111111111110001 >
b11111111111110001 E
b100 B
b11111111111100010 "
b11111111111100010 9
b11111111111100010 <
b11111111111100010 F
b110010000000000 #
b110010000000000 :
b110010000000000 D
1&
#840
0&
#845
b0 7
b0 >
b0 E
b11 A
06
02
b11111111111110001 "
b11111111111110001 9
b11111111111110001 <
b11111111111110001 F
b1000 ?
1@
b10 B
1&
#850
0&
#855
b100 A
1-
0@
b11 B
1&
#860
0&
#865
10
b11111111111110001 7
b11111111111110001 >
b11111111111110001 E
b10 A
16
12
0-
b1100100000000000 #
b1100100000000000 :
b1100100000000000 D
b11111111111100010 "
b11111111111100010 9
b11111111111100010 <
b11111111111100010 F
b100 B
1&
#870
0&
#875
b11 A
06
02
b0 7
b0 >
b0 E
1@
b10 B
b111 ?
b11111111111110001 "
b11111111111110001 9
b11111111111110001 <
b11111111111110001 F
1&
#880
0&
#885
b100 A
1-
0@
b11 B
1&
#890
0&
#895
b10 A
16
12
0-
b11111111111110010 7
b11111111111110010 >
b11111111111110010 E
b100 B
b11111111111100011 "
b11111111111100011 9
b11111111111100011 <
b11111111111100011 F
b1001000000000000 #
b1001000000000000 :
b1001000000000000 D
1&
#900
0&
#905
b1 7
b1 >
b1 E
b11 A
06
02
b11111111111110010 "
b11111111111110010 9
b11111111111110010 <
b11111111111110010 F
b110 ?
1@
b10 B
1&
#910
0&
#915
b100 A
1-
0@
b11 B
1&
#920
0&
#925
00
b11111111111110100 7
b11111111111110100 >
b11111111111110100 E
b10 A
16
12
0-
b10000000000000 #
b10000000000000 :
b10000000000000 D
b11111111111100101 "
b11111111111100101 9
b11111111111100101 <
b11111111111100101 F
b100 B
1&
#930
0&
#935
b11 A
06
02
b11 7
b11 >
b11 E
1@
b10 B
b101 ?
b11111111111110100 "
b11111111111110100 9
b11111111111110100 <
b11111111111110100 F
1&
#940
0&
#945
b100 A
1-
0@
b11 B
1&
#950
0&
#955
b10 A
16
12
0-
b11111111111110111 7
b11111111111110111 >
b11111111111110111 E
b100 B
b11111111111101000 "
b11111111111101000 9
b11111111111101000 <
b11111111111101000 F
b100000000000000 #
b100000000000000 :
b100000000000000 D
1&
#960
0&
#965
b110 7
b110 >
b110 E
b11 A
06
02
b11111111111110111 "
b11111111111110111 9
b11111111111110111 <
b11111111111110111 F
b100 ?
1@
b10 B
1&
#970
0&
#975
b100 A
1-
0@
b11 B
1&
#980
0&
#985
10
b11111111111111101 7
b11111111111111101 >
b11111111111111101 E
b10 A
16
12
0-
b1000000000000000 #
b1000000000000000 :
b1000000000000000 D
b11111111111101110 "
b11111111111101110 9
b11111111111101110 <
b11111111111101110 F
b100 B
1&
#990
0&
#995
b11 A
06
02
b1100 7
b1100 >
b1100 E
1@
b10 B
b11 ?
b11111111111111101 "
b11111111111111101 9
b11111111111111101 <
b11111111111111101 F
1&
#1000
0&
#1005
b100 A
1-
0@
b11 B
1&
#1010
0&
#1015
b10 A
16
12
0-
b1010 7
b1010 >
b1010 E
00
b100 B
b11111111111111011 "
b11111111111111011 9
b11111111111111011 <
b11111111111111011 F
b0 #
b0 :
b0 D
1&
#1020
0&
#1025
1.
0,
b11111111111111011 7
b11111111111111011 >
b11111111111111011 E
b11 A
06
02
b1010 "
b1010 9
b1010 <
b1010 F
b10 ?
1@
b10 B
1&
#1030
0&
#1035
b100 A
1-
0.
0@
b11 B
b1 #
b1 :
b1 D
1&
#1040
0&
#1045
b101 7
b101 >
b101 E
b10 A
16
12
0-
b10 #
b10 :
b10 D
b10100 "
b10100 9
b10100 <
b10100 F
b100 B
1&
#1050
0&
#1055
b11 A
1.
06
02
b11111111111110110 7
b11111111111110110 >
b11111111111110110 E
1@
b10 B
b1 ?
b101 "
b101 9
b101 <
b101 F
1&
#1060
0&
#1065
b100 A
1-
0.
b11 #
b11 :
b11 D
0@
b11 B
1&
#1070
0&
#1075
b10 A
16
12
0-
b11111111111111011 7
b11111111111111011 >
b11111111111111011 E
b100 B
b1010 "
b1010 9
b1010 <
b1010 F
b110 #
b110 :
b110 D
1&
#1080
0&
#1085
1,
b1010 7
b1010 >
b1010 E
b101 A
0.
06
02
b11111111111111011 "
b11111111111111011 9
b11111111111111011 <
b11111111111111011 F
1+
b0 ?
1@
b10 B
1&
#1090
0&
#1095
b110 A
0@
b101 B
1&
#1100
0&
#1105
b111 A
12
15
b110 B
1&
#1110
0&
#1115
b0 A
1!
02
05
0,
b11111111111111011 7
b11111111111111011 >
b11111111111111011 E
b111 B
b1010 "
b1010 9
b1010 <
b1010 F
1&
#1120
0&
#1125
0!
b0 B
1&
