raices verilog/control_raices.v
module control_raices(clk, rst, start, GE, Zero, load_D, reset_dp, init_C, shift_RD, load_R, shift_Q_1, shift_Q_0, decrease_C, done);
input clk;
input rst;
input start;
input GE;
input Zero;
output load_D;
output reset_dp;
output init_C;
output shift_RD;
output load_R;
output shift_Q_1;
output shift_Q_0;
output decrease_C;
output done;

reg [2:0]current_state;
reg [2:0]next_state;

parameter S0 = 3'd0;
parameter S1 = 3'd1;
parameter S2 = 3'd2;
parameter S3 = 3'd3;
parameter S4 = 3'd4;
parameter S5 = 3'd5;
parameter S6 = 3'd6;
parameter S7 = 3'd7;

always @(posedge clk) begin
    if (rst) begin
        current_state <= S0;
    end else begin
        current_state <= next_state;
    end
end

always @(*) begin
    case (current_state)
        S0: begin
            if (start) next_state = S1;
            else next_state = S0;
        end
        S1: begin
            next_state = S2;
        end
        S2: begin
            next_state = S3;
        end
        S3: begin
            if (GE) next_state = S4;
            else next_state = S5;
        end
        S4: begin
            next_state = S6;
        end
        S5: begin
            next_state = S6;
        end
        S6: begin
            if (Zero) next_state = S7;
            else next_state = S2;
        end
        S7: begin
            next_state = S0;
        end
        default: next_state = S0;
    endcase
end

assign load_D = (current_state == S1);
assign reset_dp = (current_state == S1);
assign init_C = (current_state == S1);
assign shift_RD = (current_state == S2);
assign load_R = (current_state == S4);
assign shift_Q_1 = (current_state == S4);
assign shift_Q_0 = (current_state == S5);
assign decrease_C = (current_state == S4) | (current_state == S5);
assign done = (current_state == S7);

endmodule

raices verilog/counter.v
module counter(clk, init_C, decrease_C, Zero);
input clk;
input init_C;
input decrease_C;
output Zero;

reg [3:0]C;

assign Zero = (C == 4'd0);

always @(posedge clk) begin
    if (init_C) begin
        C <= 4'd8;
    end else if (decrease_C) begin
        C <= C - 4'd1;
    end
end

endmodule

raices verilog/comp.v
module comp(in_R, in_T, GE);
input [9:0]in_R;
input [9:0]in_T;
output GE;

assign GE = (in_R >= in_T);

endmodule

raices verilog/subtrac.v
module subtrac(in_R, in_T, out_sub);
input [9:0]in_R;
input [9:0]in_T;
output [9:0]out_sub;

assign out_sub = in_R - in_T;

endmodule

raices verilog/gen_t.v
module gen_t(in_Q, out_T);
input [7:0]in_Q;
output [9:0]out_T;

assign out_T = {in_Q, 2'b01};

endmodule

raices verilog/reg_q.v
module reg_q(clk, rst_dp, shift_Q_1, shift_Q_0, out_Q);
input clk;
input rst_dp;
input shift_Q_1;
input shift_Q_0;
output [7:0]out_Q;

reg [7:0]Q;

assign out_Q = Q;

always @(posedge clk) begin
    if (rst_dp) begin
        Q <= 8'd0;
    end else if (shift_Q_1) begin
        Q <= {Q[6:0], 1'b1};
    end else if (shift_Q_0) begin
        Q <= {Q[6:0], 1'b0};
    end
end

endmodule

raices verilog/reg_r.v
module reg_r(clk, rst_dp, load_R, shift_RD, in_2msb, in_sub, out_R);
input clk;
input rst_dp;
input load_R;
input shift_RD;
input [1:0]in_2msb;
input [9:0]in_sub;
output [9:0]out_R;

reg [9:0]R;

assign out_R = R;

always @(posedge clk) begin
    if (rst_dp) begin
        R <= 10'd0;
    end else if (load_R) begin
        R <= in_sub;
    end else if (shift_RD) begin
        R <= {R[7:0], in_2msb};
    end
end

endmodule

raices verilog/reg_d.v
module reg_d(clk, load_D, shift_RD, in_N, out_2msb);
input clk;
input load_D;
input shift_RD;
input [15:0]in_N;
output [1:0]out_2msb;

reg [15:0]D;

assign out_2msb = D[15:14];

always @(posedge clk) begin
    if (load_D) begin
        D <= in_N;
    end else if (shift_RD) begin
        D <= {D[13:0], 2'b00};
    end
end

endmodule

raices verilog/raices.v
module raices(clk, rst, start, N, Q, R, done);
input clk;
input rst;
input start;
input [15:0] N;
output [7:0] Q;
output [9:0] R;
output done;

wire w_load_D;
wire w_reset_dp; // Señal "Reset" del diagrama para limpiar registros
wire w_init_C;
wire w_shift_RD;
wire w_load_R;
wire w_shift_Q_1;
wire w_shift_Q_0;
wire w_decrease_C;

wire w_Zero;
wire w_GE;       
wire [9:0] w_sub_out;
wire [9:0] w_T;      
wire [1:0] w_2msb_D;  

reg_d reg_d0 (.clk(clk), .load_D(w_load_D), .shift_RD(w_shift_RD), .in_N(N), .out_2msb(w_2msb_D));

reg_r reg_r0 (.clk(clk), .rst_dp(w_reset_dp), .load_R(w_load_R), .shift_RD(w_shift_RD), .in_2msb(w_2msb_D), .in_sub(w_sub_out), .out_R(R));

reg_q reg_q0 (.clk(clk), .rst_dp(w_reset_dp), .shift_Q_1(w_shift_Q_1), .shift_Q_0(w_shift_Q_0), .out_Q(Q));

gen_t gen_t0 (.in_Q(Q), .out_T(w_T));

subtrac sub0 (.in_R(R), .in_T(w_T), .out_sub(w_sub_out));

comp comp0 (.in_R(R), .in_T(w_T), .GE(w_GE));

counter count0 (.clk(clk), .init_C(w_init_C), .decrease_C(w_decrease_C), .Zero(w_Zero));

control_raices control0 (.clk(clk), .rst(rst), .start(start), .GE(w_GE), .Zero(w_Zero), .load_D(w_load_D), .reset_dp(w_reset_dp), .init_C(w_init_C), .shift_RD(w_shift_RD), .load_R(w_load_R), .shift_Q_1(w_shift_Q_1), .shift_Q_0(w_shift_Q_0), .decrease_C(w_decrease_C), .done(done));

endmodule

raices verilog/raices_tb.v
module raices_tb;

reg clk;
reg rst;
reg start;
reg [15:0]N;

wire [7:0]Q;
wire [9:0]R;
wire done;

raices dut (.clk(clk),.rst(rst),.start(start),.N(N),.Q(Q),.R(R),.done(done));

always #5 clk = ~clk;

initial begin
    $dumpfile("simulacion_raices.vcd");
    $dumpvars(0, raices_tb);

    clk = 0;
    rst = 1;
    start = 0;
    N = 16'd0;

    #10 rst = 0;

    #10 N = 16'd144; 
    start = 1;
    #10 start = 0;
    
    @(posedge done);
    $display("Prueba 1: N = %d | Raiz (Q) = %d | Residuo (R) = %d", N, Q, R);

    #20 N = 16'd625; 
    start = 1;
    #10 start = 0;
    
    @(posedge done);
    $display("Prueba 2: N = %d | Raiz (Q) = %d | Residuo (R) = %d", N, Q, R);

    #20 N = 16'd10000; 
    start = 1;
    #10 start = 0;
    
    @(posedge done);
    $display("Prueba 3: N = %d | Raiz (Q) = %d | Residuo (R) = %d", N, Q, R);

    #20 $finish;
end

endmodule

raices verilog/simulacion_raices.vcd
$date
	Mon Jul 13 13:42:16 2026
$end
$version
	Icarus Verilog
$end
$timescale
	1s
$end
$scope module raices_tb $end
$var wire 1 ! done $end
$var wire 10 " R [9:0] $end
$var wire 8 # Q [7:0] $end
$var reg 16 $ N [15:0] $end
$var reg 1 % clk $end
$var reg 1 & rst $end
$var reg 1 ' start $end
$scope module dut $end
$var wire 16 ( N [15:0] $end
$var wire 1 % clk $end
$var wire 1 & rst $end
$var wire 1 ' start $end
$var wire 10 ) w_sub_out [9:0] $end
$var wire 1 * w_shift_RD $end
$var wire 1 + w_shift_Q_1 $end
$var wire 1 , w_shift_Q_0 $end
$var wire 1 - w_reset_dp $end
$var wire 1 . w_load_R $end
$var wire 1 / w_load_D $end
$var wire 1 0 w_init_C $end
$var wire 1 1 w_decrease_C $end
$var wire 1 2 w_Zero $end
$var wire 10 3 w_T [9:0] $end
$var wire 1 4 w_GE $end
$var wire 2 5 w_2msb_D [1:0] $end
$var wire 1 ! done $end
$var wire 10 6 R [9:0] $end
$var wire 8 7 Q [7:0] $end
$scope module comp0 $end
$var wire 10 8 in_T [9:0] $end
$var wire 10 9 in_R [9:0] $end
$var wire 1 4 GE $end
$upscope $end
$scope module control0 $end
$var wire 1 4 GE $end
$var wire 1 % clk $end
$var wire 1 1 decrease_C $end
$var wire 1 & rst $end
$var wire 1 ' start $end
$var wire 1 * shift_RD $end
$var wire 1 + shift_Q_1 $end
$var wire 1 , shift_Q_0 $end
$var wire 1 - reset_dp $end
$var wire 1 . load_R $end
$var wire 1 / load_D $end
$var wire 1 0 init_C $end
$var wire 1 ! done $end
$var wire 1 2 Zero $end
$var reg 3 : current_state [2:0] $end
$var reg 3 ; next_state [2:0] $end
$upscope $end
$scope module count0 $end
$var wire 1 % clk $end
$var wire 1 1 decrease_C $end
$var wire 1 0 init_C $end
$var wire 1 2 Zero $end
$var reg 4 < C [3:0] $end
$upscope $end
$scope module gen_t0 $end
$var wire 10 = out_T [9:0] $end
$var wire 8 > in_Q [7:0] $end
$upscope $end
$scope module reg_d0 $end
$var wire 1 % clk $end
$var wire 16 ? in_N [15:0] $end
$var wire 1 / load_D $end
$var wire 1 * shift_RD $end
$var wire 2 @ out_2msb [1:0] $end
$var reg 16 A D [15:0] $end
$upscope $end
$scope module reg_q0 $end
$var wire 1 % clk $end
$var wire 8 B out_Q [7:0] $end
$var wire 1 - rst_dp $end
$var wire 1 , shift_Q_0 $end
$var wire 1 + shift_Q_1 $end
$var reg 8 C Q [7:0] $end
$upscope $end
$scope module reg_r0 $end
$var wire 1 % clk $end
$var wire 2 D in_2msb [1:0] $end
$var wire 1 . load_R $end
$var wire 10 E out_R [9:0] $end
$var wire 1 - rst_dp $end
$var wire 1 * shift_RD $end
$var wire 10 F in_sub [9:0] $end
$var reg 10 G R [9:0] $end
$upscope $end
$scope module sub0 $end
$var wire 10 H in_R [9:0] $end
$var wire 10 I in_T [9:0] $end
$var wire 10 J out_sub [9:0] $end
$upscope $end
$upscope $end
$upscope $end
$enddefinitions $end
#0
$dumpvars
bx J
bx01 I
bx H
bx G
bx F
bx E
bx D
bx C
bx B
bx A
bx @
b0 ?
bx >
bx01 =
bx <
b0 ;
bx :
bx 9
bx01 8
bx 7
bx 6
bx 5
x4
bx01 3
x2
x1
x0
x/
x.
x-
x,
x+
x*
bx )
b0 (
0'
1&
0%
b0 $
bx #
bx "
x!
$end
#5
01
0/
0-
00
0*
0.
0+
0,
0!
b0 :
1%
#10
0%
0&
#15
1%
#20
b1 ;
0%
1'
b10010000 $
b10010000 (
b10010000 ?
#25
b10 ;
1/
1-
10
b1 :
1%
#30
0%
0'
#35
b11 ;
b0 5
b0 @
b0 D
0/
0-
00
1*
b10 :
02
b1000 <
b1111111111 )
b1111111111 F
b1111111111 J
04
b1 3
b1 8
b1 =
b1 I
b0 #
b0 7
b0 >
b0 B
b0 C
b0 "
b0 6
b0 9
b0 E
b0 G
b0 H
b10010000 A
1%
#40
0%
#45
b101 ;
b1001000000 A
0*
b11 :
1%
#50
0%
#55
b110 ;
11
1,
b101 :
1%
#60
0%
#65
b10 ;
01
b111 <
0,
b110 :
1%
#70
0%
#75
b11 ;
1*
b10 :
1%
#80
0%
#85
b101 ;
b100100000000 A
0*
b11 :
1%
#90
0%
#95
b110 ;
11
1,
b101 :
1%
#100
0%
#105
b10 ;
01
b110 <
0,
b110 :
1%
#110
0%
#115
b11 ;
1*
b10 :
1%
#120
0%
#125
b101 ;
b10010000000000 A
0*
b11 :
1%
#130
0%
#135
b110 ;
11
1,
b101 :
1%
#140
0%
#145
b10 ;
01
b101 <
0,
b110 :
1%
#150
0%
#155
b11 ;
1*
b10 :
1%
#160
0%
#165
b10 5
b10 @
b10 D
b101 ;
b1001000000000000 A
0*
b11 :
1%
#170
0%
#175
b110 ;
11
1,
b101 :
1%
#180
0%
#185
b10 ;
01
b100 <
0,
b110 :
1%
#190
0%
#195
b11 ;
1*
b10 :
1%
#200
0%
#205
b1 5
b1 @
b1 D
b100 ;
b100000000000000 A
b1 )
b1 F
b1 J
14
b10 "
b10 6
b10 9
b10 E
b10 G
b10 H
0*
b11 :
1%
#210
0%
#215
b110 ;
11
1.
1+
b100 :
1%
#220
0%
#225
b10 ;
01
b1 "
b1 6
b1 9
b1 E
b1 G
b1 H
b1111111100 )
b1111111100 F
b1111111100 J
04
b101 3
b101 8
b101 =
b101 I
b1 #
b1 7
b1 >
b1 B
b1 C
b11 <
0.
0+
b110 :
1%
#230
0%
#235
b11 ;
1*
b10 :
1%
#240
0%
#245
b0 5
b0 @
b0 D
b100 ;
b0 A
b0 )
b0 F
b0 J
14
b101 "
b101 6
b101 9
b101 E
b101 G
b101 H
0*
b11 :
1%
#250
0%
#255
b110 ;
11
1.
1+
b100 :
1%
#260
0%
#265
b10 ;
01
b0 "
b0 6
b0 9
b0 E
b0 G
b0 H
b1111110011 )
b1111110011 F
b1111110011 J
04
b1101 3
b1101 8
b1101 =
b1101 I
b11 #
b11 7
b11 >
b11 B
b11 C
b10 <
0.
0+
b110 :
1%
#270
0%
#275
b11 ;
1*
b10 :
1%
#280
0%
#285
b101 ;
0*
b11 :
1%
#290
0%
#295
b110 ;
11
1,
b101 :
1%
#300
0%
#305
b10 ;
01
b1111100111 )
b1111100111 F
b1111100111 J
b11001 3
b11001 8
b11001 =
b11001 I
b110 #
b110 7
b110 >
b110 B
b110 C
b1 <
0,
b110 :
1%
#310
0%
#315
b11 ;
1*
b10 :
1%
#320
0%
#325
b101 ;
0*
b11 :
1%
#330
0%
#335
b110 ;
11
1,
b101 :
1%
#340
0%
#345
b111 ;
01
b1111001111 )
b1111001111 F
b1111001111 J
b110001 3
b110001 8
b110001 =
b110001 I
b1100 #
b1100 7
b1100 >
b1100 B
b1100 C
12
b0 <
0,
b110 :
1%
#350
0%
#355
b0 ;
1!
b111 :
1%
#360
0%
#365
0!
b0 :
1%
#370
0%
#375
1/
1-
10
b1 :
b10 ;
1%
1'
b1001110001 $
b1001110001 (
b1001110001 ?
#380
0%
#385
b11 ;
b1001110001 A
b1111111111 )
b1111111111 F
b1111111111 J
b1 3
b1 8
b1 =
b1 I
b0 #
b0 7
b0 >
b0 B
b0 C
02
b1000 <
0/
0-
00
1*
b10 :
1%
0'
#390
0%
#395
b101 ;
0*
b11 :
b100111000100 A
1%
#400
0%
#405
b110 ;
11
1,
b101 :
1%
#410
0%
#415
b10 ;
01
0,
b110 :
b111 <
1%
#420
0%
#425
b11 ;
1*
b10 :
1%
#430
0%
#435
b101 ;
0*
b11 :
b10011100010000 A
1%
#440
0%
#445
b110 ;
11
1,
b101 :
1%
#450
0%
#455
b10 ;
01
0,
b110 :
b110 <
1%
#460
0%
#465
b11 ;
1*
b10 :
1%
#470
0%
#475
b101 ;
b10 5
b10 @
b10 D
0*
b11 :
b1001110001000000 A
1%
#480
0%
#485
b110 ;
11
1,
b101 :
1%
#490
0%
#495
b10 ;
01
0,
b110 :
b101 <
1%
#500
0%
#505
b11 ;
1*
b10 :
1%
#510
0%
#515
b100 ;
b1 5
b1 @
b1 D
0*
b11 :
b1 )
b1 F
b1 J
14
b10 "
b10 6
b10 9
b10 E
b10 G
b10 H
b111000100000000 A
1%
#520
0%
#525
b110 ;
11
1.
1+
b100 :
1%
#530
0%
#535
01
b10 ;
0.
0+
b110 :
b100 <
04
b101 3
b101 8
b101 =
b101 I
b1 #
b1 7
b1 >
b1 B
b1 C
b1111111100 )
b1111111100 F
b1111111100 J
b1 "
b1 6
b1 9
b1 E
b1 G
b1 H
1%
#540
0%
#545
b11 ;
1*
b10 :
1%
#550
0%
#555
b100 ;
b11 5
b11 @
b11 D
0*
b11 :
b0 )
b0 F
b0 J
14
b101 "
b101 6
b101 9
b101 E
b101 G
b101 H
b1100010000000000 A
1%
#560
0%
#565
b110 ;
11
1.
1+
b100 :
1%
#570
0%
#575
01
b10 ;
0.
0+
b110 :
b11 <
b1101 3
b1101 8
b1101 =
b1101 I
b11 #
b11 7
b11 >
b11 B
b11 C
b1111110011 )
b1111110011 F
b1111110011 J
04
b0 "
b0 6
b0 9
b0 E
b0 G
b0 H
1%
#580
0%
#585
b11 ;
1*
b10 :
1%
#590
0%
#595
b101 ;
b0 5
b0 @
b0 D
0*
b11 :
b1111110110 )
b1111110110 F
b1111110110 J
b11 "
b11 6
b11 9
b11 E
b11 G
b11 H
b1000000000000 A
1%
#600
0%
#605
b110 ;
11
1,
b101 :
1%
#610
0%
#615
b10 ;
01
0,
b110 :
b10 <
b1111101010 )
b1111101010 F
b1111101010 J
b11001 3
b11001 8
b11001 =
b11001 I
b110 #
b110 7
b110 >
b110 B
b110 C
1%
#620
0%
#625
b11 ;
1*
b10 :
1%
#630
0%
#635
b101 ;
b1 5
b1 @
b1 D
0*
b11 :
b1111110011 )
b1111110011 F
b1111110011 J
b1100 "
b1100 6
b1100 9
b1100 E
b1100 G
b1100 H
b100000000000000 A
1%
#640
0%
#645
b110 ;
11
1,
b101 :
1%
#650
0%
#655
b10 ;
01
0,
b110 :
b1 <
b1111011011 )
b1111011011 F
b1111011011 J
b110001 3
b110001 8
b110001 =
b110001 I
b1100 #
b1100 7
b1100 >
b1100 B
b1100 C
1%
#660
0%
#665
b11 ;
1*
b10 :
1%
#670
0%
#675
b100 ;
b0 5
b0 @
b0 D
0*
b11 :
b0 )
b0 F
b0 J
14
b110001 "
b110001 6
b110001 9
b110001 E
b110001 G
b110001 H
b0 A
1%
#680
0%
#685
b110 ;
11
1.
1+
b100 :
1%
#690
0%
#695
01
b111 ;
0.
0+
b110 :
12
b0 <
b1100101 3
b1100101 8
b1100101 =
b1100101 I
b11001 #
b11001 7
b11001 >
b11001 B
b11001 C
b1110011011 )
b1110011011 F
b1110011011 J
04
b0 "
b0 6
b0 9
b0 E
b0 G
b0 H
1%
#700
0%
#705
b0 ;
1!
b111 :
1%
#710
0%
#715
0!
b0 :
1%
#720
0%
#725
1/
1-
10
b1 :
b10 ;
1%
1'
b10011100010000 $
b10011100010000 (
b10011100010000 ?
#730
0%
#735
b11 ;
0/
0-
00
1*
b10 :
02
b1000 <
b1111111111 )
b1111111111 F
b1111111111 J
b1 3
b1 8
b1 =
b1 I
b0 #
b0 7
b0 >
b0 B
b0 C
b10011100010000 A
1%
0'
#740
0%
#745
b10 5
b10 @
b10 D
b101 ;
b1001110001000000 A
0*
b11 :
1%
#750
0%
#755
b110 ;
11
1,
b101 :
1%
#760
0%
#765
b10 ;
01
b111 <
0,
b110 :
1%
#770
0%
#775
b11 ;
1*
b10 :
1%
#780
0%
#785
b1 5
b1 @
b1 D
b100 ;
b111000100000000 A
b1 )
b1 F
b1 J
14
b10 "
b10 6
b10 9
b10 E
b10 G
b10 H
0*
b11 :
1%
#790
0%
#795
b110 ;
11
1.
1+
b100 :
1%
#800
0%
#805
b10 ;
01
b1 "
b1 6
b1 9
b1 E
b1 G
b1 H
b1111111100 )
b1111111100 F
b1111111100 J
04
b101 3
b101 8
b101 =
b101 I
b1 #
b1 7
b1 >
b1 B
b1 C
b110 <
0.
0+
b110 :
1%
#810
0%
#815
b11 ;
1*
b10 :
1%
#820
0%
#825
b11 5
b11 @
b11 D
b100 ;
b1100010000000000 A
b0 )
b0 F
b0 J
14
b101 "
b101 6
b101 9
b101 E
b101 G
b101 H
0*
b11 :
1%
#830
0%
#835
b110 ;
11
1.
1+
b100 :
1%
#840
0%
#845
b10 ;
01
b0 "
b0 6
b0 9
b0 E
b0 G
b0 H
b1111110011 )
b1111110011 F
b1111110011 J
04
b1101 3
b1101 8
b1101 =
b1101 I
b11 #
b11 7
b11 >
b11 B
b11 C
b101 <
0.
0+
b110 :
1%
#850
0%
#855
b11 ;
1*
b10 :
1%
#860
0%
#865
b0 5
b0 @
b0 D
b101 ;
b1000000000000 A
b1111110110 )
b1111110110 F
b1111110110 J
b11 "
b11 6
b11 9
b11 E
b11 G
b11 H
0*
b11 :
1%
#870
0%
#875
b110 ;
11
1,
b101 :
1%
#880
0%
#885
b10 ;
01
b1111101010 )
b1111101010 F
b1111101010 J
b11001 3
b11001 8
b11001 =
b11001 I
b110 #
b110 7
b110 >
b110 B
b110 C
b100 <
0,
b110 :
1%
#890
0%
#895
b11 ;
1*
b10 :
1%
#900
0%
#905
b1 5
b1 @
b1 D
b101 ;
b100000000000000 A
b1111110011 )
b1111110011 F
b1111110011 J
b1100 "
b1100 6
b1100 9
b1100 E
b1100 G
b1100 H
0*
b11 :
1%
#910
0%
#915
b110 ;
11
1,
b101 :
1%
#920
0%
#925
b10 ;
01
b1111011011 )
b1111011011 F
b1111011011 J
b110001 3
b110001 8
b110001 =
b110001 I
b1100 #
b1100 7
b1100 >
b1100 B
b1100 C
b11 <
0,
b110 :
1%
#930
0%
#935
b11 ;
1*
b10 :
1%
#940
0%
#945
b0 5
b0 @
b0 D
b100 ;
b0 A
b0 )
b0 F
b0 J
14
b110001 "
b110001 6
b110001 9
b110001 E
b110001 G
b110001 H
0*
b11 :
1%
#950
0%
#955
b110 ;
11
1.
1+
b100 :
1%
#960
0%
#965
b10 ;
01
b0 "
b0 6
b0 9
b0 E
b0 G
b0 H
b1110011011 )
b1110011011 F
b1110011011 J
04
b1100101 3
b1100101 8
b1100101 =
b1100101 I
b11001 #
b11001 7
b11001 >
b11001 B
b11001 C
b10 <
0.
0+
b110 :
1%
#970
0%
#975
b11 ;
1*
b10 :
1%
#980
0%
#985
b101 ;
0*
b11 :
1%
#990
0%
#995
b110 ;
11
1,
b101 :
1%
#1000
0%
#1005
b10 ;
01
b1100110111 )
b1100110111 F
b1100110111 J
b11001001 3
b11001001 8
b11001001 =
b11001001 I
b110010 #
b110010 7
b110010 >
b110010 B
b110010 C
b1 <
0,
b110 :
1%
#1010
0%
#1015
b11 ;
1*
b10 :
1%
#1020
0%
#1025
b101 ;
0*
b11 :
1%
#1030
0%
#1035
b110 ;
11
1,
b101 :
1%
#1040
0%
#1045
b111 ;
01
b1001101111 )
b1001101111 F
b1001101111 J
b110010001 3
b110010001 8
b110010001 =
b110010001 I
b1100100 #
b1100100 7
b1100100 >
b1100100 B
b1100100 C
12
b0 <
0,
b110 :
1%
#1050
0%
#1055
b0 ;
1!
b111 :
1%
#1060
0%
#1065
0!
b0 :
1%
