paridad verilog/control_paridad.v
module control_paridad(clk, rst, start, x0, zero, load_x, shift_x, reset_cnt, init_c, decrease_c, inc_cnt, done);
input clk;
input rst;
input start;
input x0;
input zero;
output load_x;
output shift_x;
output reset_cnt;
output init_c;
output decrease_c;
output inc_cnt;
output done;

reg [1:0]current_state;
reg [1:0]next_state;

parameter S0 = 2'd0;
parameter S1 = 2'd1;
parameter S2 = 2'd2;
parameter S3 = 2'd3;

always @(posedge clk) begin
    if (rst) begin
        current_state <= S0;
    end else begin
        current_state <= next_state;
    end
end

always @(*) begin
    case (current_state)
        S0: begin
            if (start) next_state = S1;
            else next_state = S0;
        end
        S1: begin
            if (zero) next_state = S3;
            else next_state = S2;
        end
        S2: begin
            next_state = S1;
        end
        S3: begin
            next_state = S0;
        end
        default: next_state = S0;
    endcase
end

assign load_x = (current_state == S0);
assign reset_cnt = (current_state == S0);
assign init_c = (current_state == S0);
assign shift_x = (current_state == S2);
assign decrease_c = (current_state == S2);
assign inc_cnt = (current_state == S2) & x0;
assign done = (current_state == S3);

endmodule

BCD a Binario verilog/counter.v
module counter(clk, init_c, decrease_c, zero);
input clk;
input init_c;
input decrease_c;
output zero;

reg [4:0]c;

assign zero = (c == 5'd0);

always @(posedge clk) begin
    if (init_c) begin
        c <= 5'd16;
    end else if (decrease_c) begin
        c <= c - 5'd1;
    end
end

endmodule

paridad verilog/reg_counter.v
module reg_counter(clk, reset_cnt, inc_cnt, out_counter, out_paridad);
input clk;
input reset_cnt;
input inc_cnt;
output [4:0]out_counter;
output out_paridad;

reg [4:0]count;

assign out_counter = count;
assign out_paridad = count[0];

always @(posedge clk) begin
    if (reset_cnt) begin
        count <= 5'd0;
    end else if (inc_cnt) begin
        count <= count + 5'd1;
    end
end

endmodule

paridad verilog/reg_x.v
module reg_x(clk, load_x, shift_x, in_X, out_x0);
input clk;
input load_x;
input shift_x;
input [15:0]in_X;
output out_x0;

reg [15:0]X;

assign out_x0 = X[0];

always @(posedge clk) begin
    if (load_x) begin
        X <= in_X;
    end else if (shift_x) begin
        X <= {1'b0, X[15:1]};
    end
end

endmodule

paridad verilog/paridad.v
module paridad(clk, rst, start, X, Counter, Paridad, done);
input clk;
input rst;
input start;
input [15:0]X;
output [4:0]Counter;
output Paridad;
output done;

wire w_load_x;
wire w_shift_x;
wire w_reset_cnt;
wire w_inc_cnt;
wire w_init_c;
wire w_decrease_c;
wire w_x0;
wire w_zero;

reg_x reg_x0 (.clk(clk), .load_x(w_load_x), .shift_x(w_shift_x), .in_X(X), .out_x0(w_x0));
reg_counter reg_cnt0 (.clk(clk), .reset_cnt(w_reset_cnt), .inc_cnt(w_inc_cnt), .out_counter(Counter), .out_paridad(Paridad));
counter count0 (.clk(clk), .init_c(w_init_c), .decrease_c(w_decrease_c), .zero(w_zero));
control_paridad control0 (.clk(clk), .rst(rst), .start(start), .x0(w_x0), .zero(w_zero), .load_x(w_load_x), .shift_x(w_shift_x), .reset_cnt(w_reset_cnt), .init_c(w_init_c), .decrease_c(w_decrease_c), .inc_cnt(w_inc_cnt), .done(done));

endmodule

paridad verilog/paridad_tb.v
module paridad_tb;

reg clk;
reg rst;
reg start;
reg [15:0]X;

wire [4:0]Counter;
wire Paridad;
wire done;

paridad dut (
    .clk(clk),
    .rst(rst),
    .start(start),
    .X(X),
    .Counter(Counter),
    .Paridad(Paridad),
    .done(done)
);

always #5 clk = ~clk;

initial begin
    $dumpfile("simulacion_paridad.vcd");
    $dumpvars(0, paridad_tb);

    clk = 0;
    rst = 1;
    start = 0;
    X = 16'd0;

    #10 rst = 0;

    #10 X = 16'b0000_0000_0000_0111;
    start = 1;
    #10 start = 0;
    
    @(posedge done);
    $display("Prueba 1: X = %b | Unos contados = %d | Paridad = %b", X, Counter, Paridad);

    #20 X = 16'b1010_1010_1010_1010;
    start = 1;
    #10 start = 0;
    
    @(posedge done);
    $display("Prueba 2: X = %b | Unos contados = %d | Paridad = %b", X, Counter, Paridad);

    #20 X = 16'b0000_0000_0000_0000;
    start = 1;
    #10 start = 0;
    
    @(posedge done);
    $display("Prueba 3: X = %b | Unos contados = %d | Paridad = %b", X, Counter, Paridad);

    #20 X = 16'b1111_1111_1111_1111;
    start = 1;
    #10 start = 0;
    
    @(posedge done);
    $display("Prueba 4: X = %b | Unos contados = %d | Paridad = %b", X, Counter, Paridad);

    #20 $finish;
end

endmodule

paridad verilog/simulacion_paridad.vcd
$date
	Tue Jul 14 09:28:56 2026
$end
$version
	Icarus Verilog
$end
$timescale
	1s
$end
$scope module paridad_tb $end
$var wire 1 ! done $end
$var wire 1 " Paridad $end
$var wire 5 # Counter [4:0] $end
$var reg 16 $ X [15:0] $end
$var reg 1 % clk $end
$var reg 1 & rst $end
$var reg 1 ' start $end
$scope module dut $end
$var wire 16 ( X [15:0] $end
$var wire 1 % clk $end
$var wire 1 & rst $end
$var wire 1 ' start $end
$var wire 1 ) w_zero $end
$var wire 1 * w_x0 $end
$var wire 1 + w_shift_x $end
$var wire 1 , w_reset_cnt $end
$var wire 1 - w_load_x $end
$var wire 1 . w_init_c $end
$var wire 1 / w_inc_cnt $end
$var wire 1 0 w_decrease_c $end
$var wire 1 ! done $end
$var wire 1 " Paridad $end
$var wire 5 1 Counter [4:0] $end
$scope module control0 $end
$var wire 1 % clk $end
$var wire 1 / inc_cnt $end
$var wire 1 & rst $end
$var wire 1 ' start $end
$var wire 1 ) zero $end
$var wire 1 * x0 $end
$var wire 1 + shift_x $end
$var wire 1 , reset_cnt $end
$var wire 1 - load_x $end
$var wire 1 . init_c $end
$var wire 1 ! done $end
$var wire 1 0 decrease_c $end
$var reg 2 2 current_state [1:0] $end
$var reg 2 3 next_state [1:0] $end
$upscope $end
$scope module count0 $end
$var wire 1 % clk $end
$var wire 1 0 decrease_c $end
$var wire 1 . init_c $end
$var wire 1 ) zero $end
$var reg 5 4 c [4:0] $end
$upscope $end
$scope module reg_cnt0 $end
$var wire 1 % clk $end
$var wire 1 / inc_cnt $end
$var wire 5 5 out_counter [4:0] $end
$var wire 1 , reset_cnt $end
$var wire 1 " out_paridad $end
$var reg 5 6 count [4:0] $end
$upscope $end
$scope module reg_x0 $end
$var wire 1 % clk $end
$var wire 16 7 in_X [15:0] $end
$var wire 1 - load_x $end
$var wire 1 + shift_x $end
$var wire 1 * out_x0 $end
$var reg 16 8 X [15:0] $end
$upscope $end
$upscope $end
$upscope $end
$enddefinitions $end
#0
$dumpvars
bx 8
b0 7
bx 6
bx 5
bx 4
b0 3
bx 2
bx 1
x0
x/
x.
x-
x,
x+
x*
x)
b0 (
0'
1&
0%
b0 $
bx #
x"
x!
$end
#5
0/
1-
1,
1.
0+
00
0!
b0 2
1%
#10
0%
0&
#15
0"
0*
0)
b10000 4
b0 #
b0 1
b0 5
b0 6
b0 8
1%
#20
b1 3
0%
1'
b111 $
b111 (
b111 7
#25
1*
b10 3
b111 8
0-
0,
0.
b1 2
1%
#30
0%
0'
#35
b1 3
1/
1+
10
b10 2
1%
#40
0%
#45
1"
b10 3
0/
b11 8
b1 #
b1 1
b1 5
b1 6
b1111 4
0+
00
b1 2
1%
#50
0%
#55
b1 3
1/
1+
10
b10 2
1%
#60
0%
#65
0"
b10 3
0/
b1 8
b10 #
b10 1
b10 5
b10 6
b1110 4
0+
00
b1 2
1%
#70
0%
#75
b1 3
1/
1+
10
b10 2
1%
#80
0%
#85
0*
1"
b10 3
0/
b0 8
b11 #
b11 1
b11 5
b11 6
b1101 4
0+
00
b1 2
1%
#90
0%
#95
b1 3
1+
10
b10 2
1%
#100
0%
#105
b10 3
b1100 4
0+
00
b1 2
1%
#110
0%
#115
b1 3
1+
10
b10 2
1%
#120
0%
#125
b10 3
b1011 4
0+
00
b1 2
1%
#130
0%
#135
b1 3
1+
10
b10 2
1%
#140
0%
#145
b10 3
b1010 4
0+
00
b1 2
1%
#150
0%
#155
b1 3
1+
10
b10 2
1%
#160
0%
#165
b10 3
b1001 4
0+
00
b1 2
1%
#170
0%
#175
b1 3
1+
10
b10 2
1%
#180
0%
#185
b10 3
b1000 4
0+
00
b1 2
1%
#190
0%
#195
b1 3
1+
10
b10 2
1%
#200
0%
#205
b10 3
b111 4
0+
00
b1 2
1%
#210
0%
#215
b1 3
1+
10
b10 2
1%
#220
0%
#225
b10 3
b110 4
0+
00
b1 2
1%
#230
0%
#235
b1 3
1+
10
b10 2
1%
#240
0%
#245
b10 3
b101 4
0+
00
b1 2
1%
#250
0%
#255
b1 3
1+
10
b10 2
1%
#260
0%
#265
b10 3
b100 4
0+
00
b1 2
1%
#270
0%
#275
b1 3
1+
10
b10 2
1%
#280
0%
#285
b10 3
b11 4
0+
00
b1 2
1%
#290
0%
#295
b1 3
1+
10
b10 2
1%
#300
0%
#305
b10 3
b10 4
0+
00
b1 2
1%
#310
0%
#315
b1 3
1+
10
b10 2
1%
#320
0%
#325
b10 3
b1 4
0+
00
b1 2
1%
#330
0%
#335
b1 3
1+
10
b10 2
1%
#340
0%
#345
b11 3
1)
b0 4
0+
00
b1 2
1%
#350
0%
#355
b0 3
1!
b11 2
1%
#360
0%
#365
1-
1,
1.
0!
b0 2
1%
#370
0%
#375
0"
0-
0,
0.
b1 2
0)
b10000 4
b0 #
b0 1
b0 5
b0 6
b1010101010101010 8
b10 3
1%
1'
b1010101010101010 $
b1010101010101010 (
b1010101010101010 7
#380
0%
#385
b1 3
1+
10
b10 2
1%
0'
#390
0%
#395
b10 3
1*
0+
00
b1 2
b1111 4
b101010101010101 8
1%
#400
0%
#405
b1 3
1/
1+
10
b10 2
1%
#410
0%
#415
b10 3
0/
1"
0*
0+
00
b1 2
b1110 4
b1 #
b1 1
b1 5
b1 6
b10101010101010 8
1%
#420
0%
#425
b1 3
1+
10
b10 2
1%
#430
0%
#435
b10 3
1*
0+
00
b1 2
b1101 4
b1010101010101 8
1%
#440
0%
#445
b1 3
1/
1+
10
b10 2
1%
#450
0%
#455
b10 3
0/
0"
0*
0+
00
b1 2
b1100 4
b10 #
b10 1
b10 5
b10 6
b101010101010 8
1%
#460
0%
#465
b1 3
1+
10
b10 2
1%
#470
0%
#475
b10 3
1*
0+
00
b1 2
b1011 4
b10101010101 8
1%
#480
0%
#485
b1 3
1/
1+
10
b10 2
1%
#490
0%
#495
b10 3
0/
1"
0*
0+
00
b1 2
b1010 4
b11 #
b11 1
b11 5
b11 6
b1010101010 8
1%
#500
0%
#505
b1 3
1+
10
b10 2
1%
#510
0%
#515
b10 3
1*
0+
00
b1 2
b1001 4
b101010101 8
1%
#520
0%
#525
b1 3
1/
1+
10
b10 2
1%
#530
0%
#535
b10 3
0/
0"
0*
0+
00
b1 2
b1000 4
b100 #
b100 1
b100 5
b100 6
b10101010 8
1%
#540
0%
#545
b1 3
1+
10
b10 2
1%
#550
0%
#555
b10 3
1*
0+
00
b1 2
b111 4
b1010101 8
1%
#560
0%
#565
b1 3
1/
1+
10
b10 2
1%
#570
0%
#575
b10 3
0/
1"
0*
0+
00
b1 2
b110 4
b101 #
b101 1
b101 5
b101 6
b101010 8
1%
#580
0%
#585
b1 3
1+
10
b10 2
1%
#590
0%
#595
b10 3
1*
0+
00
b1 2
b101 4
b10101 8
1%
#600
0%
#605
b1 3
1/
1+
10
b10 2
1%
#610
0%
#615
b10 3
0/
0"
0*
0+
00
b1 2
b100 4
b110 #
b110 1
b110 5
b110 6
b1010 8
1%
#620
0%
#625
b1 3
1+
10
b10 2
1%
#630
0%
#635
b10 3
1*
0+
00
b1 2
b11 4
b101 8
1%
#640
0%
#645
b1 3
1/
1+
10
b10 2
1%
#650
0%
#655
b10 3
0/
1"
0*
0+
00
b1 2
b10 4
b111 #
b111 1
b111 5
b111 6
b10 8
1%
#660
0%
#665
b1 3
1+
10
b10 2
1%
#670
0%
#675
b10 3
1*
0+
00
b1 2
b1 4
b1 8
1%
#680
0%
#685
b1 3
1/
1+
10
b10 2
1%
#690
0%
#695
0/
b11 3
0"
0*
0+
00
b1 2
1)
b0 4
b1000 #
b1000 1
b1000 5
b1000 6
b0 8
1%
#700
0%
#705
b0 3
1!
b11 2
1%
#710
0%
#715
1-
1,
1.
0!
b0 2
1%
#720
0%
#725
b0 #
b0 1
b0 5
b0 6
0)
b10000 4
0-
0,
0.
b1 2
b10 3
1%
1'
b0 $
b0 (
b0 7
#730
0%
#735
b1 3
1+
10
b10 2
1%
0'
#740
0%
#745
b10 3
b1111 4
0+
00
b1 2
1%
#750
0%
#755
b1 3
1+
10
b10 2
1%
#760
0%
#765
b10 3
b1110 4
0+
00
b1 2
1%
#770
0%
#775
b1 3
1+
10
b10 2
1%
#780
0%
#785
b10 3
b1101 4
0+
00
b1 2
1%
#790
0%
#795
b1 3
1+
10
b10 2
1%
#800
0%
#805
b10 3
b1100 4
0+
00
b1 2
1%
#810
0%
#815
b1 3
1+
10
b10 2
1%
#820
0%
#825
b10 3
b1011 4
0+
00
b1 2
1%
#830
0%
#835
b1 3
1+
10
b10 2
1%
#840
0%
#845
b10 3
b1010 4
0+
00
b1 2
1%
#850
0%
#855
b1 3
1+
10
b10 2
1%
#860
0%
#865
b10 3
b1001 4
0+
00
b1 2
1%
#870
0%
#875
b1 3
1+
10
b10 2
1%
#880
0%
#885
b10 3
b1000 4
0+
00
b1 2
1%
#890
0%
#895
b1 3
1+
10
b10 2
1%
#900
0%
#905
b10 3
b111 4
0+
00
b1 2
1%
#910
0%
#915
b1 3
1+
10
b10 2
1%
#920
0%
#925
b10 3
b110 4
0+
00
b1 2
1%
#930
0%
#935
b1 3
1+
10
b10 2
1%
#940
0%
#945
b10 3
b101 4
0+
00
b1 2
1%
#950
0%
#955
b1 3
1+
10
b10 2
1%
#960
0%
#965
b10 3
b100 4
0+
00
b1 2
1%
#970
0%
#975
b1 3
1+
10
b10 2
1%
#980
0%
#985
b10 3
b11 4
0+
00
b1 2
1%
#990
0%
#995
b1 3
1+
10
b10 2
1%
#1000
0%
#1005
b10 3
b10 4
0+
00
b1 2
1%
#1010
0%
#1015
b1 3
1+
10
b10 2
1%
#1020
0%
#1025
b10 3
b1 4
0+
00
b1 2
1%
#1030
0%
#1035
b1 3
1+
10
b10 2
1%
#1040
0%
#1045
b11 3
1)
b0 4
0+
00
b1 2
1%
#1050
0%
#1055
b0 3
1!
b11 2
1%
#1060
0%
#1065
1-
1,
1.
0!
b0 2
1%
#1070
0%
#1075
1*
0-
0,
0.
b1 2
0)
b10000 4
b1111111111111111 8
b10 3
1%
1'
b1111111111111111 $
b1111111111111111 (
b1111111111111111 7
#1080
0%
#1085
b1 3
1/
1+
10
b10 2
1%
0'
#1090
0%
#1095
b10 3
0/
1"
0+
00
b1 2
b1111 4
b1 #
b1 1
b1 5
b1 6
b111111111111111 8
1%
#1100
0%
#1105
b1 3
1/
1+
10
b10 2
1%
#1110
0%
#1115
b10 3
0/
0"
0+
00
b1 2
b1110 4
b10 #
b10 1
b10 5
b10 6
b11111111111111 8
1%
#1120
0%
#1125
b1 3
1/
1+
10
b10 2
1%
#1130
0%
#1135
b10 3
0/
1"
0+
00
b1 2
b1101 4
b11 #
b11 1
b11 5
b11 6
b1111111111111 8
1%
#1140
0%
#1145
b1 3
1/
1+
10
b10 2
1%
#1150
0%
#1155
b10 3
0/
0"
0+
00
b1 2
b1100 4
b100 #
b100 1
b100 5
b100 6
b111111111111 8
1%
#1160
0%
#1165
b1 3
1/
1+
10
b10 2
1%
#1170
0%
#1175
b10 3
0/
1"
0+
00
b1 2
b1011 4
b101 #
b101 1
b101 5
b101 6
b11111111111 8
1%
#1180
0%
#1185
b1 3
1/
1+
10
b10 2
1%
#1190
0%
#1195
b10 3
0/
0"
0+
00
b1 2
b1010 4
b110 #
b110 1
b110 5
b110 6
b1111111111 8
1%
#1200
0%
#1205
b1 3
1/
1+
10
b10 2
1%
#1210
0%
#1215
b10 3
0/
1"
0+
00
b1 2
b1001 4
b111 #
b111 1
b111 5
b111 6
b111111111 8
1%
#1220
0%
#1225
b1 3
1/
1+
10
b10 2
1%
#1230
0%
#1235
b10 3
0/
0"
0+
00
b1 2
b1000 4
b1000 #
b1000 1
b1000 5
b1000 6
b11111111 8
1%
#1240
0%
#1245
b1 3
1/
1+
10
b10 2
1%
#1250
0%
#1255
b10 3
0/
1"
0+
00
b1 2
b111 4
b1001 #
b1001 1
b1001 5
b1001 6
b1111111 8
1%
#1260
0%
#1265
b1 3
1/
1+
10
b10 2
1%
#1270
0%
#1275
b10 3
0/
0"
0+
00
b1 2
b110 4
b1010 #
b1010 1
b1010 5
b1010 6
b111111 8
1%
#1280
0%
#1285
b1 3
1/
1+
10
b10 2
1%
#1290
0%
#1295
b10 3
0/
1"
0+
00
b1 2
b101 4
b1011 #
b1011 1
b1011 5
b1011 6
b11111 8
1%
#1300
0%
#1305
b1 3
1/
1+
10
b10 2
1%
#1310
0%
#1315
b10 3
0/
0"
0+
00
b1 2
b100 4
b1100 #
b1100 1
b1100 5
b1100 6
b1111 8
1%
#1320
0%
#1325
b1 3
1/
1+
10
b10 2
1%
#1330
0%
#1335
b10 3
0/
1"
0+
00
b1 2
b11 4
b1101 #
b1101 1
b1101 5
b1101 6
b111 8
1%
#1340
0%
#1345
b1 3
1/
1+
10
b10 2
1%
#1350
0%
#1355
b10 3
0/
0"
0+
00
b1 2
b10 4
b1110 #
b1110 1
b1110 5
b1110 6
b11 8
1%
#1360
0%
#1365
b1 3
1/
1+
10
b10 2
1%
#1370
0%
#1375
b10 3
0/
1"
0+
00
b1 2
b1 4
b1111 #
b1111 1
b1111 5
b1111 6
b1 8
1%
#1380
0%
#1385
b1 3
1/
1+
10
b10 2
1%
#1390
0%
#1395
0/
b11 3
0"
0*
0+
00
b1 2
1)
b0 4
b10000 #
b10000 1
b10000 5
b10000 6
b0 8
1%
#1400
0%
#1405
b0 3
1!
b11 2
1%
#1410
0%
#1415
1-
1,
1.
0!
b0 2
1%
#1420
0%
#1425
1*
b1111111111111111 8
b0 #
b0 1
b0 5
b0 6
0)
b10000 4
1%
