Multiplicador_verilog/rcd.v
module rcd (clk, in_B, shift, load, s_B);
input clk;
input [15:0]in_B;
input load;
input shift;
output reg [15:0]s_B;

always @(posedge clk) begin
    if (load) begin
        s_B = in_B; 
    end else if (shift) begin
        s_B <= {1'b0, s_B[15:1]}; // Shift left by 1 bit, filling with 0
    end
end

endmodule

Multiplicador_verilog/rcd_TB.v
`timescale 1ns / 1ps
`define SIMULATION

module rcd_TB;

    reg        clk;
    reg [15:0] in_B;
    reg        load;
    reg        shift;


    rcd uut( .clk(clk), .in_B(in_B), .load(load), .shift(shift) );

    parameter PERIOD          = 20;
    parameter real DUTY_CYCLE = 0.5;
    parameter OFFSET          = 0;

    initial  begin  // Process for clk
        #OFFSET;
        forever
        begin
            clk = 1'b0;
            #(PERIOD-(PERIOD*DUTY_CYCLE)) clk = 1'b1;
            #(PERIOD*DUTY_CYCLE);
        end
    end

    initial begin
        #0 in_B = 2567; load = 0; shift = 0;
        @ (negedge clk);
        load  = 1;
        @ (negedge clk);
        load  = 0;

        repeat(23) begin
            @(negedge clk);
            shift= 1;
            @(negedge clk);
            shift = 0;
        end
    end

    initial begin: TEST_CASE
        $dumpfile("rcd_TB.vcd");
        $dumpvars(-1, uut);
        #(100000) $finish;
    end

endmodule

Multiplicador_verilog/rcd_TB.vcd
$date
	Mon May 25 08:50:52 2026
$end
$version
	Icarus Verilog
$end
$timescale
	1ps
$end
$scope module rcd_TB $end
$scope module uut $end
$var wire 1 ! clk $end
$var wire 16 " in_B [15:0] $end
$var wire 1 # load $end
$var wire 1 $ shift $end
$var reg 16 % s_B [15:0] $end
$upscope $end
$upscope $end
$enddefinitions $end
#0
$dumpvars
bx %
0$
0#
b101000000111 "
0!
$end
#10000
1!
#20000
1#
0!
#30000
b101000000111 %
1!
#40000
0#
0!
#50000
1!
#60000
1$
0!
#70000
b10100000011 %
1!
#80000
0$
0!
#90000
1!
#100000
1$
0!
#110000
b1010000001 %
1!
#120000
0$
0!
#130000
1!
#140000
1$
0!
#150000
b101000000 %
1!
#160000
0$
0!
#170000
1!
#180000
1$
0!
#190000
b10100000 %
1!
#200000
0$
0!
#210000
1!
#220000
1$
0!
#230000
b1010000 %
1!
#240000
0$
0!
#250000
1!
#260000
1$
0!
#270000
b101000 %
1!
#280000
0$
0!
#290000
1!
#300000
1$
0!
#310000
b10100 %
1!
#320000
0$
0!
#330000
1!
#340000
1$
0!
#350000
b1010 %
1!
#360000
0$
0!
#370000
1!
#380000
1$
0!
#390000
b101 %
1!
#400000
0$
0!
#410000
1!
#420000
1$
0!
#430000
b10 %
1!
#440000
0$
0!
#450000
1!
#460000
1$
0!
#470000
b1 %
1!
#480000
0$
0!
#490000
1!
#500000
1$
0!
#510000
b0 %
1!
#520000
0$
0!
#530000
1!
#540000
1$
0!
#550000
1!
#560000
0$
0!
#570000
1!
#580000
1$
0!
#590000
1!
#600000
0$
0!
#610000
1!
#620000
1$
0!
#630000
1!
#640000
0$
0!
#650000
1!
#660000
1$
0!
#670000
1!
#680000
0$
0!
#690000
1!
#700000
1$
0!
#710000
1!
#720000
0$
0!
#730000
1!
#740000
1$
0!
#750000
1!
#760000
0$
0!
#770000
1!
#780000
1$
0!
#790000
1!
#800000
0$
0!
#810000
1!
#820000
1$
0!
#830000
1!
#840000
0$
0!
#850000
1!
#860000
1$
0!
#870000
1!
#880000
0$
0!
#890000
1!
#900000
1$
0!
#910000
1!
#920000
0$
0!
#930000
1!
#940000
1$
0!
#950000
1!
#960000
0$
0!
