Multiplicador_verilog/control_multi.v
module control_multi (
    input clk,
    input rst,
    input init,
    input lsb_B,
    input z,
    output reg load,
    output reg init_c,
    output reg dec_c,
    output reg add,
    output reg sh,
    output reg done,
    output reg reset
);

    // Definición de estados
    localparam IDLE  = 2'd0;
    localparam ADD   = 2'd1;
    localparam SHIFT = 2'd2;
    localparam DONE  = 2'd3;

    reg [1:0] state, next_state;

    // Memoria de estado
    always @(posedge clk or posedge rst) begin
        if (rst)
            state <= IDLE;
        else
            state <= next_state;
    end

    // Lógica combinacional de siguiente estado y salidas
    always @(*) begin
        // Valores por defecto para evitar latches
        load   = 0;
        init_c = 0;
        add    = 0;
        sh     = 0;
        dec_c  = 0;
        done   = 0;
        reset  = 0;
        next_state = state;

        case (state)
            IDLE: begin
                if (init) begin
                    load = 1;
                    init_c = 1;
                    next_state = ADD;
                end
            end
            
            ADD: begin
                if (lsb_B) 
                    add = 1; // Solo suma si el bit menos significativo es 1
                next_state = SHIFT;
            end
            
            SHIFT: begin
                sh = 1;
                dec_c = 1; // Reduce el contador
                if (z) 
                    next_state = DONE; // Al procesar 16 bits, terminamos
                else 
                    next_state = ADD;  
            end
            
            DONE: begin
                done = 1;
                next_state = IDLE;
            end
            
            default: next_state = IDLE;
        endcase
    end
endmodule

Multiplicador_verilog/acc.v
module acc (
    input clk,
    input [31:0] A,
    input add,
    input rst, // Se conecta a w_load para limpiar al inicio
    output reg [31:0] r
);
    always @(posedge clk) begin
        if (rst)
            r <= 32'b0; // Limpia el acumulador
        else if (add)
            r <= r + A; // Suma el valor desplazado de A
    end
endmodule

Multiplicador_verilog/comp.v
module comp (
    input clk,
    input init_c,
    input dec_c,
    output z
);
    reg [4:0] count;

    always @(posedge clk) begin
        if (init_c)
            count <= 5'd16; // Inicia la cuenta en 16
        else if (dec_c && !z)
            count <= count - 1'b1; // Decrementa en 1
    end

    // La señal z es 1 cuando el contador llega a 0
    assign z = (count == 5'd0);
endmodule

Multiplicador_verilog/rci.v
module rci (
    input clk,
    input [15:0] in_A,
    input shift,
    input load,
    output reg [31:0] s_A
);
    always @(posedge clk) begin
        if (load)
            s_A <= {16'b0, in_A};
        else if (shift)
            s_A <= {s_A[30:0], 1'b0}; // Desplaza a la izquierda
    end
endmodule

Multiplicador_verilog/rcd.v
module rcd (clk, in_B, shift, load, s_B);
input clk;
input [15:0]in_B;
input load;
input shift;
output reg [15:0]s_B;

always @(posedge clk) begin
    if (load) begin
        s_B = in_B; 
    end else if (shift) begin
        s_B <= {1'b0, s_B[15:1]}; // Shift left by 1 bit, filling with 0
    end
end

endmodule

Multiplicador_verilog/mult.v
module mult(clk,rst,init,A,B,r,done);
input rst;
input clk;
input init;
input [15:0]A;
input [15:0]B;
output[31:0]r;
output done;

wire w_shft;
wire w_reset;
wire w_load;
wire w_add;
wire w_init_c;
wire w_dec_c;
wire w_zero;



wire [31:0]w_A;
wire [15:0]w_B;


rcd rcd0 (.clk(clk), .in_B(B), .shift(w_shft), .load(w_load), .s_B(w_B));
rci rci0 (.clk(clk), .in_A(A), .shift(w_shft), .load(w_load), .s_A(w_A));
comp comp0 (.clk(clk), .init_c(w_init_c), .dec_c(w_dec_c), .z(w_zero));
acc acc0(.clk(clk), .A(w_A), .add(w_add), .rst(w_load), .r(r));
control_multi control0 (.clk(clk), .rst(rst), .load(w_load), .lsb_B(w_B[0]), .init(init), .z(w_zero), .done(done), .sh(w_shft), .reset(w_reset), .init_c(w_init_c), .dec_c(w_dec_c), .add(w_add) );

endmodule

Multiplicador_verilog/tb_mult.v
`timescale 1ns / 1ps

module tb_mult;

    // 1. Declarar señales 
    reg clk;
    reg rst;
    reg init;
    reg [15:0] A;
    reg [15:0] B;
    
    wire [31:0] r;
    wire done;

    // 2. Instanciar el módulo TOP 
    mult uut (
        .clk(clk),
        .rst(rst),
        .init(init),
        .A(A),
        .B(B),
        .r(r),     
        .done(done)
    );

    // 3. Generar el reloj (cambio de estado 5 nanosegundos)
    always #5 clk = ~clk;

    // 4. Bloque inicial para inyectar los estímulos
    initial begin
        
        $dumpfile("simulacion.vcd");
        $dumpvars(0, tb_mult);

        // Estado inicial
        clk = 0;
        rst = 1;
        init = 0;
        A = 0;
        B = 0;

        
        #10 rst = 0;

        // --- PRUEBA 1: Multiplicar 5 * 3 ---
        #10;
        A = 16'd5;
        B = 16'd3;
        init = 1;     // Damos la orden de iniciar
        #10 init = 0; // Bajamos la señal para que no reinicie el proceso
        
        // Esperamos a que el módulo nos avise que terminó
        wait(done == 1);
        $display("Tiempo: %0t | Prueba 1: %d * %d = %d", $time, A, B, r);

        // --- PRUEBA 2: Multiplicar 12 * 12 ---
        #20;
        A = 16'd12;
        B = 16'd12;
        init = 1;
        #10 init = 0;
        
        wait(done == 1);
        $display("Tiempo: %0t | Prueba 2: %d * %d = %d", $time, A, B, r);

        // Terminamos la simulación
        #20 $finish;
    end

endmodule

Multiplicador_verilog/simulacion.vcd
$date
	Mon Jun 01 07:35:04 2026
$end
$version
	Icarus Verilog
$end
$timescale
	1ps
$end
$scope module tb_mult $end
$var wire 32 ! r [31:0] $end
$var wire 1 " done $end
$var reg 16 # A [15:0] $end
$var reg 16 $ B [15:0] $end
$var reg 1 % clk $end
$var reg 1 & init $end
$var reg 1 ' rst $end
$scope module uut $end
$var wire 16 ( A [15:0] $end
$var wire 16 ) B [15:0] $end
$var wire 1 % clk $end
$var wire 1 & init $end
$var wire 1 ' rst $end
$var wire 1 * w_zero $end
$var wire 1 + w_shft $end
$var wire 1 , w_reset $end
$var wire 1 - w_load $end
$var wire 1 . w_init_c $end
$var wire 1 / w_dec_c $end
$var wire 1 0 w_add $end
$var wire 16 1 w_B [15:0] $end
$var wire 32 2 w_A [31:0] $end
$var wire 32 3 r [31:0] $end
$var wire 1 " done $end
$scope module acc0 $end
$var wire 1 % clk $end
$var wire 1 - rst $end
$var wire 1 0 add $end
$var wire 32 4 A [31:0] $end
$var reg 32 5 r [31:0] $end
$upscope $end
$scope module comp0 $end
$var wire 1 % clk $end
$var wire 1 * z $end
$var wire 1 . init_c $end
$var wire 1 / dec_c $end
$var reg 5 6 count [4:0] $end
$upscope $end
$scope module control0 $end
$var wire 1 % clk $end
$var wire 1 & init $end
$var wire 1 7 lsb_B $end
$var wire 1 ' rst $end
$var wire 1 * z $end
$var reg 1 0 add $end
$var reg 1 / dec_c $end
$var reg 1 " done $end
$var reg 1 . init_c $end
$var reg 1 - load $end
$var reg 2 8 next_state [1:0] $end
$var reg 1 , reset $end
$var reg 1 + sh $end
$var reg 2 9 state [1:0] $end
$upscope $end
$scope module rcd0 $end
$var wire 1 % clk $end
$var wire 16 : in_B [15:0] $end
$var wire 1 - load $end
$var wire 1 + shift $end
$var reg 16 ; s_B [15:0] $end
$upscope $end
$scope module rci0 $end
$var wire 1 % clk $end
$var wire 16 < in_A [15:0] $end
$var wire 1 - load $end
$var wire 1 + shift $end
$var reg 32 = s_A [31:0] $end
$upscope $end
$upscope $end
$upscope $end
$enddefinitions $end
#0
$dumpvars
bx =
b0 <
bx ;
b0 :
b0 9
b0 8
x7
bx 6
bx 5
bx 4
bx 3
bx 2
bx 1
00
0/
0.
0-
0,
0+
x*
b0 )
b0 (
1'
0&
0%
b0 $
b0 #
0"
bx !
$end
#5000
1%
#10000
0%
0'
#15000
1%
#20000
b1 8
1.
1-
0%
1&
b11 $
b11 )
b11 :
b101 #
b101 (
b101 <
#25000
10
b101 2
b101 4
b101 =
0*
b10000 6
b0 !
b0 3
b0 5
b1 9
b10 8
0.
0-
17
b11 1
b11 ;
1%
#30000
b10 8
10
0%
0&
#35000
b1 8
1/
1+
00
b101 !
b101 3
b101 5
b10 9
1%
#40000
0%
#45000
b10 8
10
0/
0+
b1 1
b1 ;
b1010 2
b1010 4
b1010 =
b1111 6
b1 9
1%
#50000
0%
#55000
b1 8
1/
1+
00
b1111 !
b1111 3
b1111 5
b10 9
1%
#60000
0%
#65000
07
b10 8
00
0/
0+
b0 1
b0 ;
b10100 2
b10100 4
b10100 =
b1110 6
b1 9
1%
#70000
0%
#75000
b1 8
1/
1+
b10 9
1%
#80000
0%
#85000
b10 8
0/
0+
b101000 2
b101000 4
b101000 =
b1101 6
b1 9
1%
#90000
0%
#95000
b1 8
1/
1+
b10 9
1%
#100000
0%
#105000
b10 8
0/
0+
b1010000 2
b1010000 4
b1010000 =
b1100 6
b1 9
1%
#110000
0%
#115000
b1 8
1/
1+
b10 9
1%
#120000
0%
#125000
b10 8
0/
0+
b10100000 2
b10100000 4
b10100000 =
b1011 6
b1 9
1%
#130000
0%
#135000
b1 8
1/
1+
b10 9
1%
#140000
0%
#145000
b10 8
0/
0+
b101000000 2
b101000000 4
b101000000 =
b1010 6
b1 9
1%
#150000
0%
#155000
b1 8
1/
1+
b10 9
1%
#160000
0%
#165000
b10 8
0/
0+
b1010000000 2
b1010000000 4
b1010000000 =
b1001 6
b1 9
1%
#170000
0%
#175000
b1 8
1/
1+
b10 9
1%
#180000
0%
#185000
b10 8
0/
0+
b10100000000 2
b10100000000 4
b10100000000 =
b1000 6
b1 9
1%
#190000
0%
#195000
b1 8
1/
1+
b10 9
1%
#200000
0%
#205000
b10 8
0/
0+
b101000000000 2
b101000000000 4
b101000000000 =
b111 6
b1 9
1%
#210000
0%
#215000
b1 8
1/
1+
b10 9
1%
#220000
0%
#225000
b10 8
0/
0+
b1010000000000 2
b1010000000000 4
b1010000000000 =
b110 6
b1 9
1%
#230000
0%
#235000
b1 8
1/
1+
b10 9
1%
#240000
0%
#245000
b10 8
0/
0+
b10100000000000 2
b10100000000000 4
b10100000000000 =
b101 6
b1 9
1%
#250000
0%
#255000
b1 8
1/
1+
b10 9
1%
#260000
0%
#265000
b10 8
0/
0+
b101000000000000 2
b101000000000000 4
b101000000000000 =
b100 6
b1 9
1%
#270000
0%
#275000
b1 8
1/
1+
b10 9
1%
#280000
0%
#285000
b10 8
0/
0+
b1010000000000000 2
b1010000000000000 4
b1010000000000000 =
b11 6
b1 9
1%
#290000
0%
#295000
b1 8
1/
1+
b10 9
1%
#300000
0%
#305000
b10 8
0/
0+
b10100000000000000 2
b10100000000000000 4
b10100000000000000 =
b10 6
b1 9
1%
#310000
0%
#315000
b1 8
1/
1+
b10 9
1%
#320000
0%
#325000
b10 8
0/
0+
b101000000000000000 2
b101000000000000000 4
b101000000000000000 =
b1 6
b1 9
1%
#330000
0%
#335000
b1 8
1/
1+
b10 9
1%
#340000
0%
#345000
b10 8
0/
0+
b1010000000000000000 2
b1010000000000000000 4
b1010000000000000000 =
1*
b0 6
b1 9
1%
#350000
0%
#355000
b11 8
1/
1+
b10 9
1%
#360000
0%
#365000
b0 8
1"
0/
0+
b10100000000000000000 2
b10100000000000000000 4
b10100000000000000000 =
b11 9
1%
#370000
0%
#375000
0"
b0 9
1%
#380000
0%
#385000
b1100 2
b1100 4
b1100 =
0*
b10000 6
b0 !
b0 3
b0 5
b1 9
b1100 1
b1100 ;
b10 8
0.
0-
1%
1&
b1100 $
b1100 )
b1100 :
b1100 #
b1100 (
b1100 <
#390000
0%
#395000
1/
1+
b10 9
b1 8
1%
0&
#400000
0%
#405000
b10 8
0/
0+
b110 1
b110 ;
b11000 2
b11000 4
b11000 =
b1111 6
b1 9
1%
#410000
0%
#415000
b1 8
1/
1+
b10 9
1%
#420000
0%
#425000
10
17
b10 8
0/
0+
b11 1
b11 ;
b110000 2
b110000 4
b110000 =
b1110 6
b1 9
1%
#430000
0%
#435000
b1 8
1/
1+
00
b110000 !
b110000 3
b110000 5
b10 9
1%
#440000
0%
#445000
b10 8
10
0/
0+
b1 1
b1 ;
b1100000 2
b1100000 4
b1100000 =
b1101 6
b1 9
1%
#450000
0%
#455000
b1 8
1/
1+
00
b10010000 !
b10010000 3
b10010000 5
b10 9
1%
#460000
0%
#465000
07
b10 8
00
0/
0+
b0 1
b0 ;
b11000000 2
b11000000 4
b11000000 =
b1100 6
b1 9
1%
#470000
0%
#475000
b1 8
1/
1+
b10 9
1%
#480000
0%
#485000
b10 8
0/
0+
b110000000 2
b110000000 4
b110000000 =
b1011 6
b1 9
1%
#490000
0%
#495000
b1 8
1/
1+
b10 9
1%
#500000
0%
#505000
b10 8
0/
0+
b1100000000 2
b1100000000 4
b1100000000 =
b1010 6
b1 9
1%
#510000
0%
#515000
b1 8
1/
1+
b10 9
1%
#520000
0%
#525000
b10 8
0/
0+
b11000000000 2
b11000000000 4
b11000000000 =
b1001 6
b1 9
1%
#530000
0%
#535000
b1 8
1/
1+
b10 9
1%
#540000
0%
#545000
b10 8
0/
0+
b110000000000 2
b110000000000 4
b110000000000 =
b1000 6
b1 9
1%
#550000
0%
#555000
b1 8
1/
1+
b10 9
1%
#560000
0%
#565000
b10 8
0/
0+
b1100000000000 2
b1100000000000 4
b1100000000000 =
b111 6
b1 9
1%
#570000
0%
#575000
b1 8
1/
1+
b10 9
1%
#580000
0%
#585000
b10 8
0/
0+
b11000000000000 2
b11000000000000 4
b11000000000000 =
b110 6
b1 9
1%
#590000
0%
#595000
b1 8
1/
1+
b10 9
1%
#600000
0%
#605000
b10 8
0/
0+
b110000000000000 2
b110000000000000 4
b110000000000000 =
b101 6
b1 9
1%
#610000
0%
#615000
b1 8
1/
1+
b10 9
1%
#620000
0%
#625000
b10 8
0/
0+
b1100000000000000 2
b1100000000000000 4
b1100000000000000 =
b100 6
b1 9
1%
#630000
0%
#635000
b1 8
1/
1+
b10 9
1%
#640000
0%
#645000
b10 8
0/
0+
b11000000000000000 2
b11000000000000000 4
b11000000000000000 =
b11 6
b1 9
1%
#650000
0%
#655000
b1 8
1/
1+
b10 9
1%
#660000
0%
#665000
b10 8
0/
0+
b110000000000000000 2
b110000000000000000 4
b110000000000000000 =
b10 6
b1 9
1%
#670000
0%
#675000
b1 8
1/
1+
b10 9
1%
#680000
0%
#685000
b10 8
0/
0+
b1100000000000000000 2
b1100000000000000000 4
b1100000000000000000 =
b1 6
b1 9
1%
#690000
0%
#695000
b1 8
1/
1+
b10 9
1%
#700000
0%
#705000
b10 8
0/
0+
b11000000000000000000 2
b11000000000000000000 4
b11000000000000000000 =
1*
b0 6
b1 9
1%
#710000
0%
#715000
b11 8
1/
1+
b10 9
1%
#720000
0%
#725000
b0 8
1"
0/
0+
b110000000000000000000 2
b110000000000000000000 4
b110000000000000000000 =
b11 9
1%
#730000
0%
#735000
0"
b0 9
1%
